Workbook

Sheet Cover Page
A4: =TODAY() -> 45776
A6: Semantic Web for Valuation
A7: Deliverable 1: Approximation Valuation Model for Mobile Apps
A8: BY
A9: Chen Li, Prachi Mishra, Yilin Xie

Sheet Assumption Table
A1: Assumption Table
B3: KPIs Assumptions
B4: Organic Downloads
B5: Mean | C5: 10000
B6: Stdev | C6: 1000
B7: Growth rate | C7: 0.02
B8: Paid Downloads*via marketing
B9: Mean | C9: 5000
B10: Stdev | C10: 100
B11: Growth rate | C11: 0.02
B12: Retention Rate
B13: Mean | C13: 0.5
B14: Stdev | C14: 0.1
B16: Revenue Assumptions
B17: 1.Licensing
B18: Price of the App | C18: 1.99
B20: 2.Subscription
C21: average revenue per user per month | D21: Conversion Rate(Mean) | E21: Conversion Rate(Stdev)
B22: Monthly plan | C22: 10.99 | D22: 0.3 | E22: 0.1
B23: Annual plan | C23: 8.33 | D23: 0.3 | E23: 0.1
B24: No plan | C24: 10.99 | D24: 0 | E24: 0
B26: 3. In-app purchase
C27: Price | D27: Conversion Rate(Mean) | E27: Conversion Rate(Stdev) | F27: Average repeated times
B28: item 1 - Pricing | C28: 4.99 | D28: 0.4 | E28: 0.1 | F28: 1.5
B29: item 2 - Pricing | C29: 9.9 | D29: 0.3 | E29: 0.1 | F29: 1
B30: item 3 - Pricing | C30: 19.99 | D30: 0.2 | E30: 0.1 | F30: 2
B31: item 4 - Pricing | C31: 29.99 | D31: 0.1 | E31: 0.1 | F31: 1
B33: 4. Advertisement
B34: Impressions | D34: Conversion rate (Mean) | E34: Conversion rate (Std Dev)
B35: Mean | C35: 10000 | D35: 0.2 | E35: 0.1
B36: Stdev | C36: 1000
B37: Click-Through Rate (CTR)
B38: Mean | C38: 0.25
B39: Stdev | C39: 0.005
B40: Revenue/Cost per Click (CPC) | C40: 0.7
B42: 5. Commission
B43: Transactions | C43: # of transactions
B44: Mean | C44: 100
B45: Stdev | C45: 0.1
B46: Growth rate | C46: 0.05
B47: average revenue per transaction | C47: 100
C49: commision rate
B50: Marketplace/platform Commissions | C50: 0.2 | D50: based on industry average
B53: Costs of Goods Sold Assumption
C54: (% of Revenue)
B55: Hosting and Infrastructure | C55: 0.03
B56: Development and Maintenance | C56: 0.15
B57: Customer Support
B58: active users per support agent | C58: 500
B59: average compensation per agent per month | C59: 2000
B60: Content Licensing | C60: 0.01
B61: Platform fees | C61: 0.3
B62: Payment Processing Fees | C62: % of transactions | D62: % of revenue
B63: Credit Card | C63: 0.1 | D63: 0.015
B64: PayPal | C64: 0.2 | D64: 0.0349
B65: Square | C65: 0.1 | D65: 0.029
B66: Stripe | C66: 0.05 | D66: 0.029
B67: Total | C67: 1 | D67: =SUMPRODUCT(C63:C66,D63:D66) -> 0.01283
B69: Expenses Assumption
B70: Research & Development expense | C70: 650 | D70: recurring monthly expense
B71: General & Admin expense | C71: 0.05 | D71: as % of revenue
B72: Office Space | C72: 10000 | D72: monthly recurring expense
B73: Annual Growth Rate | C73: 0.02 | D73: inflation
B74: Sales & Marketing
B75: Fixed | C75: 5000 | D75: Estimated as industry average
B76: Variable(Cost per download) | C76: 1 | D76: Estimated as industry average
B77: Technology and Infrastructure | C77: 0.1 | D77: as % of revenue
B78: Other Operating Expenses | C78: 0.01 | D78: as % of revenue
B80: Capital Expenditure & Depreciation Assumptions
B81: Assumed Depreciation Method: | C81: Straight-line
B82: Assets | C82: Useful life(in months) | D82: CapEx
B83: Technology Infrastructure
B84: Servers and Data Centers | C84: 60 | D84: 0.03 | E84: as % of Revenue
B85: Networking Equipment | C85: 60 | D85: 0.01 | E85: as % of Revenue
B86: Software and Licenses
B87: Enterprise Software | C87: 120 | D87: 0.02
B88: Software Licenses | C88: 60 | D88: 0.01
B89: Hardware
B90: Computers and Workstations | C90: 60 | D90: 0.01
B91: Storage Devices | C91: 60 | D91: 0.02
B92: Development Costs
B93: Product Development | C93: 60 | D93: 0.05
B94: Research and Development | C94: 60 | D94: 0.02
B95: Intellectual Property
B96: Patents and Trademarks | C96: 240 | D96: 0.005
B97: Proprietary Technology | C97: 120 | D97: 0.02
B98: Cloud Services
B99: Long-term Cloud Contracts | C99: 60 | D99: 0.03
B100: Security
B101: Cybersecurity Infrastructure | C101: 60 | D101: 0.02
B104: Long Term Debt Assumptions | C104: Value | D104: Notes
B105: Beginning Debt Level as (2023) in $ | C105: 5000000 | D105: Estimated starting debt for the company
B106: Long Term Lease, Level | C106: 500 | D106: Estimated long-term lease obligations | E106: Monthly
B107: Long Term Debt Growth Rate | C107: 0.02 | D107: Expected annual growth in debt | E107: =2%/12 -> 0.0016666667
B108: Interest rate on long term debt | C108: 0.04 | D108: Based on current market rates | E108: =4%/12 -> 0.0033333333
B109: Long Term Debt Repayment During forecast period | C109: 0.085 | D109: Scheduled debt repayment | E109: =8.5%/12 -> 0.0070833333
B110: Tax rate assumed in this model | C110: 0.21 | D110: Estimated effective tax rate
B111: Dividend Payout Ratio | C111: 0.4 | D111: Estimated average based on past years
B114: Working Capital Assumptions | C114: Value | D114: Notes
B115: Cash and ST Investments | C115: 0.05 | D115: As a % of revenue
...

Sheet Projection Model
A1: Projection Model
B2: 1 | C2: 2 | D2: 3 | E2: 4 | F2: 5 | G2: 6 | H2: 7 | I2: 8 | J2: 9 | K2: 10 | L2: 11 | M2: 12 | N2: 13 | O2: 14 | P2: 15 | Q2: 16 | R2: 17 | S2: 18 | T2: 19 | U2: 20 | V2: 21 | W2: 22 | X2: 23 | Y2: 24 | Z2: 25 | AA2: 26 | AB2: 27 | AC2: 28 | AD2: 29 | AE2: 30 | AF2: 31 | AG2: 32 | AH2: 33 | AI2: 34 | AJ2: 35 | AK2: 36 | AL2: 37 | AM2: 38 | AN2: 39 | AO2: 40 | AP2: 41 | AQ2: 42 | AR2: 43 | AS2: 44 | AT2: 45 | AU2: 46 | AV2: 47 | AW2: 48 | AX2: 49 | AY2: 50 | AZ2: 51 | BA2: 52 | BB2: 53 | BC2: 54 | BD2: 55 | BE2: 56 | BF2: 57 | BG2: 58 | BH2: 59 | BI2: 60 | BK2: 1 | BL2: 2 | BM2: 3 | BN2: 4 | BO2: 5
A3: KPIs Schedule | BJ3: =A3 -> KPIs Schedule
B4: 1 | C4: =B4+1 -> 2 | D4: =C4+1 -> 3 | E4: =D4+1 -> 4 | F4: =E4+1 -> 5 | G4: =F4+1 -> 6 | H4: =G4+1 -> 7 | I4: =H4+1 -> 8 | J4: =I4+1 -> 9 | ... BI4: =BH4+1 -> 60 | BK4: 1 | BL4: =BK4+1 -> 2 | BM4: =BL4+1 -> 3 | BN4: =BM4+1 -> 4 | BO4: =BN4+1 -> 5
A5: Organic Downloads | B5: =ROUND(MAX(0,NORMINV(RAND(), B6, 'Assumption Table'!$C$6)),0) -> 11111 | C5: =ROUND(MAX(0,NORMINV(RAND(), C6, 'Assumption Table'!$C$6)),0) -> 10631 | D5: =ROUND(MAX(0,NORMINV(RAND(), D6, 'Assumption Table'!$C$6)),0) -> 9960 | E5: =ROUND(MAX(0,NORMINV(RAND(), E6, 'Assumption Table'!$C$6)),0) -> 10410 | F5: =ROUND(MAX(0,NORMINV(RAND(), F6, 'Assumption Table'!$C$6)),0) -> 9486 | G5: =ROUND(MAX(0,NORMINV(RAND(), G6, 'Assumption Table'!$C$6)),0) -> 10687 | H5: =ROUND(MAX(0,NORMINV(RAND(), H6, 'Assumption Table'!$C$6)),0) -> 12027 | I5: =ROUND(MAX(0,NORMINV(RAND(), I6, 'Assumption Table'!$C$6)),0) -> 10157 | ... BI5: =ROUND(MAX(0,NORMINV(RAND(), BI6, 'Assumption Table'!$C$6)),0) -> 29639 | BJ5: =A5 -> Organic Downloads | BK5: =SUMIFS($B5:$BI5,$B$4:$BI$4,"<=12") -> 130043 | BL5: =SUMIFS($B5:$BI5,$B$4:$BI$4,"<=24",$B$4:$BI$4,">12") -> 166099 | BM5: =SUMIFS($B5:$BI5,$B$4:$BI$4,"<=36",$B$4:$BI$4,">24") -> 211871 | BN5: =SUMIFS($B5:$BI5,$B$4:$BI$4,"<=48",$B$4:$BI$4,">36") -> 272189 | BO5: =SUMIFS($B5:$BI5,$B$4:$BI$4,"<=60",$B$4:$BI$4,">48") -> 351801
A6: Mean | B6: ='Assumption Table'!C5 -> 10000 | C6: =ROUND(B6*(1+'Assumption Table'!$C$7),0) -> 10200 | D6: =ROUND(C6*(1+'Assumption Table'!$C$7),0) -> 10404 | E6: =ROUND(D6*(1+'Assumption Table'!$C$7),0) -> 10612 | F6: =ROUND(E6*(1+'Assumption Table'!$C$7),0) -> 10824 | G6: =ROUND(F6*(1+'Assumption Table'!$C$7),0) -> 11040 | H6: =ROUND(G6*(1+'Assumption Table'!$C$7),0) -> 11261 | I6: =ROUND(H6*(1+'Assumption Table'!$C$7),0) -> 11486 | J6: =ROUND(I6*(1+'Assumption Table'!$C$7),0) -> 11716 | ... BI6: =ROUND(BH6*(1+'Assumption Table'!$C$7),0) -> 32164
A7: Paid Downloads | B7: =ROUND(MAX(0,NORMINV(RAND(), B8, 'Assumption Table'!$C$10)),0) -> 5017 | C7: =ROUND(MAX(0,NORMINV(RAND(), C8, 'Assumption Table'!$C$10)),0) -> 4922 | D7: =ROUND(MAX(0,NORMINV(RAND(), D8, 'Assumption Table'!$C$10)),0) -> 5195 | E7: =ROUND(MAX(0,NORMINV(RAND(), E8, 'Assumption Table'!$C$10)),0) -> 5210 | F7: =ROUND(MAX(0,NORMINV(RAND(), F8, 'Assumption Table'!$C$10)),0) -> 5384 | G7: =ROUND(MAX(0,NORMINV(RAND(), G8, 'Assumption Table'!$C$10)),0) -> 5426 | H7: =ROUND(MAX(0,NORMINV(RAND(), H8, 'Assumption Table'!$C$10)),0) -> 5545 | I7: =ROUND(MAX(0,NORMINV(RAND(), I8, 'Assumption Table'!$C$10)),0) -> 5740 | ... BI7: =ROUND(MAX(0,NORMINV(RAND(), BI8, 'Assumption Table'!$C$10)),0) -> 16135 | BJ7: =A7 -> Paid Downloads | BK7: =SUMIFS($B7:$BI7,$B$4:$BI$4,"<=12") -> 66699 | BL7: =SUMIFS($B7:$BI7,$B$4:$BI$4,"<=24",$B$4:$BI$4,">12") -> 85321 | BM7: =SUMIFS($B7:$BI7,$B$4:$BI$4,"<=36",$B$4:$BI$4,">24") -> 108341 | BN7: =SUMIFS($B7:$BI7,$B$4:$BI$4,"<=48",$B$4:$BI$4,">36") -> 136488 | BO7: =SUMIFS($B7:$BI7,$B$4:$BI$4,"<=60",$B$4:$BI$4,">48") -> 173450
A8: Mean | B8: ='Assumption Table'!C9 -> 5000 | C8: =ROUND(B8*(1+'Assumption Table'!$C$11),0) -> 5100 | D8: =ROUND(C8*(1+'Assumption Table'!$C$11),0) -> 5202 | E8: =ROUND(D8*(1+'Assumption Table'!$C$11),0) -> 5306 | F8: =ROUND(E8*(1+'Assumption Table'!$C$11),0) -> 5412 | G8: =ROUND(F8*(1+'Assumption Table'!$C$11),0) -> 5520 | H8: =ROUND(G8*(1+'Assumption Table'!$C$11),0) -> 5630 | I8: =ROUND(H8*(1+'Assumption Table'!$C$11),0) -> 5743 | J8: =ROUND(I8*(1+'Assumption Table'!$C$11),0) -> 5858 | ... BI8: =ROUND(BH8*(1+'Assumption Table'!$C$11),0) -> 16087
A9: Total New Downloads | B9: =SUM(B5,B7) -> 16128 | C9: =SUM(C5,C7) -> 15553 | D9: =SUM(D5,D7) -> 15155 | E9: =SUM(E5,E7) -> 15620 | F9: =SUM(F5,F7) -> 14870 | G9: =SUM(G5,G7) -> 16113 | H9: =SUM(H5,H7) -> 17572 | I9: =SUM(I5,I7) -> 15897 | ... BI9: =SUM(BI5,BI7) -> 45774 | BJ9: =A9 -> Total New Downloads | BK9: =SUMIFS($B9:$BI9,$B$4:$BI$4,"<=12") -> 196742 | BL9: =SUMIFS($B9:$BI9,$B$4:$BI$4,"<=24",$B$4:$BI$4,">12") -> 251420 | BM9: =SUMIFS($B9:$BI9,$B$4:$BI$4,"<=36",$B$4:$BI$4,">24") -> 320212 | BN9: =SUMIFS($B9:$BI9,$B$4:$BI$4,"<=48",$B$4:$BI$4,">36") -> 408677 | BO9: =SUMIFS($B9:$BI9,$B$4:$BI$4,"<=60",$B$4:$BI$4,">48") -> 525251
A10: Cumulative Downloads | B10: =B9 -> 16128 | C10: =B10+C9 -> 31681 | D10: =C10+D9 -> 46836 | E10: =D10+E9 -> 62456 | F10: =E10+F9 -> 77326 | G10: =F10+G9 -> 93439 | H10: =G10+H9 -> 111011 | I10: =H10+I9 -> 126908 | J10: =I10+J9 -> 143876 | ... BI10: =BH10+BI9 -> 1702302 | BJ10: =A10 -> Cumulative Downloads | BK10: =SUMIFS($B10:$BI10,$B$4:$BI$4,"=12") -> 196742 | BL10: =SUMIFS($B10:$BI10,$B$4:$BI$4,"=24") -> 448162 | BM10: =SUMIFS($B10:$BI10,$B$4:$BI$4,"=36") -> 768374 | BN10: =SUMIFS($B10:$BI10,$B$4:$BI$4,"=48") -> 1177051 | BO10: =SUMIFS($B10:$BI10,$B$4:$BI$4,"=60") -> 1702302
BJ11: =A11 -> 0
A12: Retention rate | B12: =MAX(0, MIN(1, NORMINV(RAND(), 'Assumption Table'!$C$13, 'Assumption Table'!$C$14))) -> 0.47590206 | C12: =MAX(0, MIN(1, NORMINV(RAND(), 'Assumption Table'!$C$13, 'Assumption Table'!$C$14))) -> 0.53473812 | D12: =MAX(0, MIN(1, NORMINV(RAND(), 'Assumption Table'!$C$13, 'Assumption Table'!$C$14))) -> 0.56285626 | E12: =MAX(0, MIN(1, NORMINV(RAND(), 'Assumption Table'!$C$13, 'Assumption Table'!$C$14))) -> 0.40676654 | F12: =MAX(0, MIN(1, NORMINV(RAND(), 'Assumption Table'!$C$13, 'Assumption Table'!$C$14))) -> 0.54053542 | G12: =MAX(0, MIN(1, NORMINV(RAND(), 'Assumption Table'!$C$13, 'Assumption Table'!$C$14))) -> 0.51296365 | H12: =MAX(0, MIN(1, NORMINV(RAND(), 'Assumption Table'!$C$13, 'Assumption Table'!$C$14))) -> 0.48736059 | I12: =MAX(0, MIN(1, NORMINV(RAND(), 'Assumption Table'!$C$13, 'Assumption Table'!$C$14))) -> 0.52229978 | ... BI12: =MAX(0, MIN(1, NORMINV(RAND(), 'Assumption Table'!$C$13, 'Assumption Table'!$C$14))) -> 0.57144063
A13: Churn rate | B13: =1-B12 -> 0.52409794 | C13: =1-C12 -> 0.46526188 | D13: =1-D12 -> 0.43714374 | E13: =1-E12 -> 0.59323346 | F13: =1-F12 -> 0.45946458 | G13: =1-G12 -> 0.48703635 | H13: =1-H12 -> 0.51263941 | I13: =1-I12 -> 0.47770022 | ... BI13: =1-BI12 -> 0.42855937
A14: Active Users | B14: =ROUND(B10*B12,0) -> 7675 | C14: =ROUND(C10*C12,0) -> 16941 | D14: =ROUND(D10*D12,0) -> 26362 | E14: =ROUND(E10*E12,0) -> 25405 | F14: =ROUND(F10*F12,0) -> 41797 | G14: =ROUND(G10*G12,0) -> 47931 | H14: =ROUND(H10*H12,0) -> 54102 | I14: =ROUND(I10*I12,0) -> 66284 | ... BI14: =ROUND(BI10*BI12,0) -> 972765 | BJ14: =A14 -> Active Users | BK14: =SUMIFS($B14:$BI14,$B$4:$BI$4,"=12") -> 76633 | BL14: =SUMIFS($B14:$BI14,$B$4:$BI$4,"=24") -> 215639 | BM14: =SUMIFS($B14:$BI14,$B$4:$BI$4,"=36") -> 300273 | BN14: =SUMIFS($B14:$BI14,$B$4:$BI$4,"=48") -> 446275 | BO14: =SUMIFS($B14:$BI14,$B$4:$BI$4,"=60") -> 972765
BJ15: =A15 -> 0
A16: Revenue Schedule | BJ16: =A16 -> Revenue Schedule
B17: 1 | C17: 2 | D17: 3 | E17: 4 | F17: 5 | G17: 6 | H17: 7 | I17: 8 | J17: 9 | K17: 10 | L17: 11 | M17: 12 | N17: 13 | O17: 14 | P17: 15 | Q17: 16 | R17: 17 | S17: 18 | T17: 19 | U17: 20 | V17: 21 | W17: 22 | X17: 23 | Y17: 24 | Z17: 25 | AA17: 26 | AB17: 27 | AC17: 28 | AD17: 29 | AE17: 30 | AF17: 31 | AG17: 32 | AH17: 33 | AI17: 34 | AJ17: 35 | AK17: 36 | AL17: 37 | AM17: 38 | AN17: 39 | AO17: 40 | AP17: 41 | AQ17: 42 | AR17: 43 | AS17: 44 | AT17: 45 | AU17: 46 | AV17: 47 | AW17: 48 | AX17: 49 | AY17: 50 | AZ17: 51 | BA17: 52 | BB17: 53 | BC17: 54 | BD17: 55 | BE17: 56 | BF17: 57 | BG17: 58 | BH17: 59 | BI17: 60 | BJ17: =A17 -> 0 | BK17: 1 | BL17: 2 | BM17: 3 | BN17: 4 | BO17: 5
A18: ='Assumption Table'!B17 -> 1.Licensing | BJ18: =A18 -> 1.Licensing
A19: Revenue from Licensing | B19: ='Assumption Table'!$C$18*B9 -> 32094.72 | C19: ='Assumption Table'!$C$18*C9 -> 30950.47 | D19: ='Assumption Table'!$C$18*D9 -> 30158.45 | E19: ='Assumption Table'!$C$18*E9 -> 31083.8 | F19: ='Assumption Table'!$C$18*F9 -> 29591.3 | G19: ='Assumption Table'!$C$18*G9 -> 32064.87 | H19: ='Assumption Table'!$C$18*H9 -> 34968.28 | I19: ='Assumption Table'!$C$18*I9 -> 31635.03 | ... BI19: ='Assumption Table'!$C$18*BI9 -> 91090.26 | BJ19: =A19 -> Revenue from Licensing | BK19: =SUMIFS($B19:$BI19,$B$4:$BI$4,"<=12") -> 391516.58 | BL19: =SUMIFS($B19:$BI19,$B$4:$BI$4,"<=24",$B$4:$BI$4,">12") -> 500325.8 | BM19: =SUMIFS($B19:$BI19,$B$4:$BI$4,"<=36",$B$4:$BI$4,">24") -> 637221.88 | BN19: =SUMIFS($B19:$BI19,$B$4:$BI$4,"<=48",$B$4:$BI$4,">36") -> 813267.23 | BO19: =SUMIFS($B19:$BI19,$B$4:$BI$4,"<=60",$B$4:$BI$4,">48") -> 1045249.5
BJ20: =A20 -> 0
A21: ='Assumption Table'!B20 -> 2.Subscription | BJ21: =A21 -> 2.Subscription
A22: Monthly Plan | B22: ='Assumption Table'!$C$22*B23*B14 -> 35411.567 | C22: ='Assumption Table'!$C$22*C23*C14 -> 70246.79 | D22: ='Assumption Table'!$C$22*D23*D14 -> 124901.54 | E22: ='Assumption Table'!$C$22*E23*E14 -> 114484.66 | F22: ='Assumption Table'!$C$22*F23*F14 -> 105018.28 | G22: ='Assumption Table'!$C$22*G23*G14 -> 144524.11 | H22: ='Assumption Table'!$C$22*H23*H14 -> 136815.63 | I22: ='Assumption Table'!$C$22*I23*I14 -> 176908.12 | ... BI22: ='Assumption Table'!$C$22*BI23*BI14 -> 3306877.5 | BJ22: =A22 -> Monthly Plan | BK22: =SUMIFS($B22:$BI22,$B$4:$BI$4,"<=12") -> 2143474.5 | BL22: =SUMIFS($B22:$BI22,$B$4:$BI$4,"<=24",$B$4:$BI$4,">12") -> 7044753.1 | BM22: =SUMIFS($B22:$BI22,$B$4:$BI$4,"<=36",$B$4:$BI$4,">24") -> 12398382 | BN22: =SUMIFS($B22:$BI22,$B$4:$BI$4,"<=48",$B$4:$BI$4,">36") -> 16977451 | BO22: =SUMIFS($B22:$BI22,$B$4:$BI$4,"<=60",$B$4:$BI$4,">48") -> 31668971
A23: Conversion Rate | B23: =MAX(0,MIN(1,NORMINV(RAND(),'Assumption Table'!$D$22,'Assumption Table'!$E$22))) -> 0.41982575 | C23: =MAX(0,MIN(1,NORMINV(RAND(),'Assumption Table'!$D$22,'Assumption Table'!$E$22))) -> 0.37730256 | D23: =MAX(0,MIN(1,NORMINV(RAND(),'Assumption Table'!$D$22,'Assumption Table'!$E$22))) -> 0.43111362 | E23: =MAX(0,MIN(1,NORMINV(RAND(),'Assumption Table'!$D$22,'Assumption Table'!$E$22))) -> 0.41004396 | F23: =MAX(0,MIN(1,NORMINV(RAND(),'Assumption Table'!$D$22,'Assumption Table'!$E$22))) -> 0.22862415 | G23: =MAX(0,MIN(1,NORMINV(RAND(),'Assumption Table'!$D$22,'Assumption Table'!$E$22))) -> 0.27436336 | H23: =MAX(0,MIN(1,NORMINV(RAND(),'Assumption Table'!$D$22,'Assumption Table'!$E$22))) -> 0.23010429 | I23: =MAX(0,MIN(1,NORMINV(RAND(),'Assumption Table'!$D$22,'Assumption Table'!$E$22))) -> 0.24285182 | ... BI23: =MAX(0,MIN(1,NORMINV(RAND(),'Assumption Table'!$D$22,'Assumption Table'!$E$22))) -> 0.30932319
A24: Annual Plan | B24: ='Assumption Table'!$C$23*B25*B14 -> 19571.066 | C24: ='Assumption Table'!$C$23*C25*C14 -> 52451.155 | D24: ='Assumption Table'!$C$23*D25*D14 -> 56893.433 | E24: ='Assumption Table'!$C$23*E25*E14 -> 54574.341 | F24: ='Assumption Table'!$C$23*F25*F14 -> 26446.288 | G24: ='Assumption Table'!$C$23*G25*G14 -> 183040.24 | H24: ='Assumption Table'!$C$23*H25*H14 -> 179484.11 | I24: ='Assumption Table'!$C$23*I25*I14 -> 196886.43 | ... BI24: ='Assumption Table'!$C$23*BI25*BI14 -> 1703972.1 | BJ24: =A24 -> Annual Plan | BK24: =SUMIFS($B24:$BI24,$B$4:$BI$4,"<=12") -> 1766820.1 | BL24: =SUMIFS($B24:$BI24,$B$4:$BI$4,"<=24",$B$4:$BI$4,">12") -> 3907849 | BM24: =SUMIFS($B24:$BI24,$B$4:$BI$4,"<=36",$B$4:$BI$4,">24") -> 9464077.2 | BN24: =SUMIFS($B24:$BI24,$B$4:$BI$4,"<=48",$B$4:$BI$4,">36") -> 17213742 | BO24: =SUMIFS($B24:$BI24,$B$4:$BI$4,"<=60",$B$4:$BI$4,">48") -> 22524934
A25: Conversion Rate | B25: =MAX(0,MIN(1-B23,NORMINV(RAND(),'Assumption Table'!$D$23,'Assumption Table'!$E$23))) -> 0.30611957 | C25: =MAX(0,MIN(1-C23,NORMINV(RAND(),'Assumption Table'!$D$23,'Assumption Table'!$E$23))) -> 0.37168156 | D25: =MAX(0,MIN(1-D23,NORMINV(RAND(),'Assumption Table'!$D$23,'Assumption Table'!$E$23))) -> 0.25908292 | E25: =MAX(0,MIN(1-E23,NORMINV(RAND(),'Assumption Table'!$D$23,'Assumption Table'!$E$23))) -> 0.25788394 | F25: =MAX(0,MIN(1-F23,NORMINV(RAND(),'Assumption Table'!$D$23,'Assumption Table'!$E$23))) -> 0.075958192 | G25: =MAX(0,MIN(1-G23,NORMINV(RAND(),'Assumption Table'!$D$23,'Assumption Table'!$E$23))) -> 0.45844272 | H25: =MAX(0,MIN(1-H23,NORMINV(RAND(),'Assumption Table'!$D$23,'Assumption Table'!$E$23))) -> 0.39826092 | I25: =MAX(0,MIN(1-I23,NORMINV(RAND(),'Assumption Table'!$D$23,'Assumption Table'!$E$23))) -> 0.35658418 | ... BI25: =MAX(0,MIN(1-BI23,NORMINV(RAND(),'Assumption Table'!$D$23,'Assumption Table'!$E$23))) -> 0.21028561
A26: Total revenue from Subscription | B26: =SUM(B22,B24) -> 54982.634 | C26: =SUM(C22,C24) -> 122697.94 | D26: =SUM(D22,D24) -> 181794.97 | E26: =SUM(E22,E24) -> 169059.01 | F26: =SUM(F22,F24) -> 131464.57 | G26: =SUM(G22,G24) -> 327564.35 | H26: =SUM(H22,H24) -> 316299.75 | I26: =SUM(I22,I24) -> 373794.54 | ... BI26: =SUM(BI22,BI24) -> 5010849.7 | BJ26: =A26 -> Total revenue from Subscription | BK26: =SUMIFS($B26:$BI26,$B$4:$BI$4,"<=12") -> 3910294.6 | BL26: =SUMIFS($B26:$BI26,$B$4:$BI$4,"<=24",$B$4:$BI$4,">12") -> 10952602 | BM26: =SUMIFS($B26:$BI26,$B$4:$BI$4,"<=36",$B$4:$BI$4,">24") -> 21862460 | BN26: =SUMIFS($B26:$BI26,$B$4:$BI$4,"<=48",$B$4:$BI$4,">36") -> 34191194 | BO26: =SUMIFS($B26:$BI26,$B$4:$BI$4,"<=60",$B$4:$BI$4,">48") -> 54193905
BJ27: =A27 -> 0
A28: ='Assumption Table'!B26 -> 3. In-app purchase | BJ28: =A28 -> 3. In-app purchase
A29: item 1 | B29: ='Assumption Table'!$C$28*B30*B$14*'Assumption Table'!$F$28 -> 23202.648 | C29: ='Assumption Table'!$C$28*C30*C$14*'Assumption Table'!$F$28 -> 56264.674 | D29: ='Assumption Table'!$C$28*D30*D$14*'Assumption Table'!$F$28 -> 54019.767 | E29: ='Assumption Table'!$C$28*E30*E$14*'Assumption Table'!$F$28 -> 65148.401 | F29: ='Assumption Table'!$C$28*F30*F$14*'Assumption Table'!$F$28 -> 104741.91 | G29: ='Assumption Table'!$C$28*G30*G$14*'Assumption Table'!$F$28 -> 184419.28 | H29: ='Assumption Table'!$C$28*H30*H$14*'Assumption Table'!$F$28 -> 131592.46 | I29: ='Assumption Table'!$C$28*I30*I$14*'Assumption Table'!$F$28 -> 206292.52 | ... BI29: ='Assumption Table'!$C$28*BI30*BI$14*'Assumption Table'!$F$28 -> 2777066.2 | BJ29: =A29 -> item 1 | BK29: =SUMIFS($B29:$BI29,$B$4:$BI$4,"<=12") -> 1926243 | BL29: =SUMIFS($B29:$BI29,$B$4:$BI$4,"<=24",$B$4:$BI$4,">12") -> 7023309.1 | BM29: =SUMIFS($B29:$BI29,$B$4:$BI$4,"<=36",$B$4:$BI$4,">24") -> 11414757 | BN29: =SUMIFS($B29:$BI29,$B$4:$BI$4,"<=48",$B$4:$BI$4,">36") -> 19128234 | BO29: =SUMIFS($B29:$BI29,$B$4:$BI$4,"<=60",$B$4:$BI$4,">48") -> 26128283
A30: Conversion Rate | B30: =MAX(0,MIN(1,NORMINV(RAND(),'Assumption Table'!$D$28,'Assumption Table'!$E$28))) -> 0.40389396 | C30: =MAX(0,MIN(1,NORMINV(RAND(),'Assumption Table'!$D$28,'Assumption Table'!$E$28))) -> 0.44371586 | D30: =MAX(0,MIN(1,NORMINV(RAND(),'Assumption Table'!$D$28,'Assumption Table'!$E$28))) -> 0.27376791 | E30: =MAX(0,MIN(1,NORMINV(RAND(),'Assumption Table'!$D$28,'Assumption Table'!$E$28))) -> 0.34260426 | F30: =MAX(0,MIN(1,NORMINV(RAND(),'Assumption Table'!$D$28,'Assumption Table'!$E$28))) -> 0.33479857 | G30: =MAX(0,MIN(1,NORMINV(RAND(),'Assumption Table'!$D$28,'Assumption Table'!$E$28))) -> 0.51404131 | H30: =MAX(0,MIN(1,NORMINV(RAND(),'Assumption Table'!$D$28,'Assumption Table'!$E$28))) -> 0.32495699 | I30: =MAX(0,MIN(1,NORMINV(RAND(),'Assumption Table'!$D$28,'Assumption Table'!$E$28))) -> 0.41579854 | ... BI30: =MAX(0,MIN(1,NORMINV(RAND(),'Assumption Table'!$D$28,'Assumption Table'!$E$28))) -> 0.3814051
A31: item 2 | B31: ='Assumption Table'!$C$29*B32*B$14*'Assumption Table'!$F$29 -> 28386.906 | C31: ='Assumption Table'!$C$29*C32*C$14*'Assumption Table'!$F$29 -> 68367.121 | D31: ='Assumption Table'!$C$29*D32*D$14*'Assumption Table'!$F$29 -> 73544.401 | E31: ='Assumption Table'!$C$29*E32*E$14*'Assumption Table'!$F$29 -> 48303.884 | F31: ='Assumption Table'!$C$29*F32*F$14*'Assumption Table'!$F$29 -> 149140.49 | G31: ='Assumption Table'!$C$29*G32*G$14*'Assumption Table'!$F$29 -> 150433.91 | H31: ='Assumption Table'!$C$29*H32*H$14*'Assumption Table'!$F$29 -> 68155.091 | I31: ='Assumption Table'!$C$29*I32*I$14*'Assumption Table'!$F$29 -> 200899.75 | ... BI31: ='Assumption Table'!$C$29*BI32*BI$14*'Assumption Table'!$F$29 -> 2794379 | BJ31: =A31 -> item 2 | BK31: =SUMIFS($B31:$BI31,$B$4:$BI$4,"<=12") -> 1964295.3 | BL31: =SUMIFS($B31:$BI31,$B$4:$BI$4,"<=24",$B$4:$BI$4,">12") -> 5485108.5 | BM31: =SUMIFS($B31:$BI31,$B$4:$BI$4,"<=36",$B$4:$BI$4,">24") -> 10263633 | BN31: =SUMIFS($B31:$BI31,$B$4:$BI$4,"<=48",$B$4:$BI$4,">36") -> 17067420 | BO31: =SUMIFS($B31:$BI31,$B$4:$BI$4,"<=60",$B$4:$BI$4,">48") -> 26350747
A32: Conversion Rate | B32: =MAX(0,MIN(1,NORMINV(RAND(),'Assumption Table'!$D$29,'Assumption Table'!$E$29))) -> 0.37359794 | C32: =MAX(0,MIN(1,NORMINV(RAND(),'Assumption Table'!$D$29,'Assumption Table'!$E$29))) -> 0.40763649 | D32: =MAX(0,MIN(1,NORMINV(RAND(),'Assumption Table'!$D$29,'Assumption Table'!$E$29))) -> 0.28179681 | E32: =MAX(0,MIN(1,NORMINV(RAND(),'Assumption Table'!$D$29,'Assumption Table'!$E$29))) -> 0.1920559 | F32: =MAX(0,MIN(1,NORMINV(RAND(),'Assumption Table'!$D$29,'Assumption Table'!$E$29))) -> 0.3604253 | G32: =MAX(0,MIN(1,NORMINV(RAND(),'Assumption Table'!$D$29,'Assumption Table'!$E$29))) -> 0.3170254 | H32: =MAX(0,MIN(1,NORMINV(RAND(),'Assumption Table'!$D$29,'Assumption Table'!$E$29))) -> 0.12724766 | I32: =MAX(0,MIN(1,NORMINV(RAND(),'Assumption Table'!$D$29,'Assumption Table'!$E$29))) -> 0.30615086 | ... BI32: =MAX(0,MIN(1,NORMINV(RAND(),'Assumption Table'!$D$29,'Assumption Table'!$E$29))) -> 0.2901631
A33: item 3 | B33: ='Assumption Table'!$C$30*B34*B$14 -> 38679.598 | C33: ='Assumption Table'!$C$30*C34*C$14 -> 0 | D33: ='Assumption Table'!$C$30*D34*D$14 -> 150023.03 | E33: ='Assumption Table'!$C$30*E34*E$14 -> 103642.48 | F33: ='Assumption Table'!$C$30*F34*F$14 -> 79310.653 | G33: ='Assumption Table'!$C$30*G34*G$14 -> 163353.18 | H33: ='Assumption Table'!$C$30*H34*H$14 -> 295280.89 | I33: ='Assumption Table'!$C$30*I34*I$14 -> 369793.17 | ... BI33: ='Assumption Table'!$C$30*BI34*BI$14 -> 3281726.4 | BJ33: =A33 -> item 3 | BK33: =SUMIFS($B33:$BI33,$B$4:$BI$4,"<=12") -> 2588651.7 | BL33: =SUMIFS($B33:$BI33,$B$4:$BI$4,"<=24",$B$4:$BI$4,">12") -> 11734036 | BM33: =SUMIFS($B33:$BI33,$B$4:$BI$4,"<=36",$B$4:$BI$4,">24") -> 16511338 | BN33: =SUMIFS($B33:$BI33,$B$4:$BI$4,"<=48",$B$4:$BI$4,">36") -> 20681451 | BO33: =SUMIFS($B33:$BI33,$B$4:$BI$4,"<=60",$B$4:$BI$4,">48") -> 30925516
A34: Conversion Rate | B34: =MAX(0,MIN(1,NORMINV(RAND(),'Assumption Table'!$D$30,'Assumption Table'!$E$30))) -> 0.25211041 | C34: =MAX(0,MIN(1,NORMINV(RAND(),'Assumption Table'!$D$30,'Assumption Table'!$E$30))) -> 0 | D34: =MAX(0,MIN(1,NORMINV(RAND(),'Assumption Table'!$D$30,'Assumption Table'!$E$30))) -> 0.28468645 | E34: =MAX(0,MIN(1,NORMINV(RAND(),'Assumption Table'!$D$30,'Assumption Table'!$E$30))) -> 0.20408251 | F34: =MAX(0,MIN(1,NORMINV(RAND(),'Assumption Table'!$D$30,'Assumption Table'!$E$30))) -> 0.094923474 | G34: =MAX(0,MIN(1,NORMINV(RAND(),'Assumption Table'!$D$30,'Assumption Table'!$E$30))) -> 0.17048977 | H34: =MAX(0,MIN(1,NORMINV(RAND(),'Assumption Table'!$D$30,'Assumption Table'!$E$30))) -> 0.27302928 | I34: =MAX(0,MIN(1,NORMINV(RAND(),'Assumption Table'!$D$30,'Assumption Table'!$E$30))) -> 0.27908557 | ... BI34: =MAX(0,MIN(1,NORMINV(RAND(),'Assumption Table'!$D$30,'Assumption Table'!$E$30))) -> 0.16876471
A35: item 4 | B35: ='Assumption Table'!$C$31*B36*B$14 -> 993.92139 | C35: ='Assumption Table'!$C$31*C36*C$14 -> 69548.383 | D35: ='Assumption Table'!$C$31*D36*D$14 -> 193458.3 | E35: ='Assumption Table'!$C$31*E36*E$14 -> 61041.594 | F35: ='Assumption Table'!$C$31*F36*F$14 -> 148924.75 | G35: ='Assumption Table'!$C$31*G36*G$14 -> 247973.61 | H35: ='Assumption Table'!$C$31*H36*H$14 -> 217977.47 | I35: ='Assumption Table'!$C$31*I36*I$14 -> 307276.03 | ... BI35: ='Assumption Table'!$C$31*BI36*BI$14 -> 5179589.5 | BJ35: =A35 -> item 4 | BK35: =SUMIFS($B35:$BI35,$B$4:$BI$4,"<=12") -> 2538930.6 | BL35: =SUMIFS($B35:$BI35,$B$4:$BI$4,"<=24",$B$4:$BI$4,">12") -> 7406410 | BM35: =SUMIFS($B35:$BI35,$B$4:$BI$4,"<=36",$B$4:$BI$4,">24") -> 14996446 | BN35: =SUMIFS($B35:$BI35,$B$4:$BI$4,"<=48",$B$4:$BI$4,">36") -> 17309233 | BO35: =SUMIFS($B35:$BI35,$B$4:$BI$4,"<=60",$B$4:$BI$4,">48") -> 37442038
A36: Conversion Rate | B36: =MAX(0,MIN(1,NORMINV(RAND(),'Assumption Table'!$D$31,'Assumption Table'!$E$31))) -> 0.0043181447 | C36: =MAX(0,MIN(1,NORMINV(RAND(),'Assumption Table'!$D$31,'Assumption Table'!$E$31))) -> 0.13688994 | D36: =MAX(0,MIN(1,NORMINV(RAND(),'Assumption Table'!$D$31,'Assumption Table'!$E$31))) -> 0.2446992 | E36: =MAX(0,MIN(1,NORMINV(RAND(),'Assumption Table'!$D$31,'Assumption Table'!$E$31))) -> 0.080118018 | F36: =MAX(0,MIN(1,NORMINV(RAND(),'Assumption Table'!$D$31,'Assumption Table'!$E$31))) -> 0.1188079 | G36: =MAX(0,MIN(1,NORMINV(RAND(),'Assumption Table'!$D$31,'Assumption Table'!$E$31))) -> 0.1725093 | H36: =MAX(0,MIN(1,NORMINV(RAND(),'Assumption Table'!$D$31,'Assumption Table'!$E$31))) -> 0.1343451 | I36: =MAX(0,MIN(1,NORMINV(RAND(),'Assumption Table'!$D$31,'Assumption Table'!$E$31))) -> 0.15457651 | ... BI36: =MAX(0,MIN(1,NORMINV(RAND(),'Assumption Table'!$D$31,'Assumption Table'!$E$31))) -> 0.17754602
A37: Total revenue from In app Purchase | B37: =SUM(B29,B31,B33,B35) -> 91263.073 | C37: =SUM(C29,C31,C33,C35) -> 194180.18 | D37: =SUM(D29,D31,D33,D35) -> 471045.5 | E37: =SUM(E29,E31,E33,E35) -> 278136.36 | F37: =SUM(F29,F31,F33,F35) -> 482117.82 | G37: =SUM(G29,G31,G33,G35) -> 746179.97 | H37: =SUM(H29,H31,H33,H35) -> 713005.91 | I37: =SUM(I29,I31,I33,I35) -> 1084261.5 | ... BI37: =SUM(BI29,BI31,BI33,BI35) -> 14032761 | BJ37: =A37 -> Total revenue from In app Purchase | BK37: =SUMIFS($B37:$BI37,$B$4:$BI$4,"<=12") -> 9018120.6 | BL37: =SUMIFS($B37:$BI37,$B$4:$BI$4,"<=24",$B$4:$BI$4,">12") -> 31648864 | BM37: =SUMIFS($B37:$BI37,$B$4:$BI$4,"<=36",$B$4:$BI$4,">24") -> 53186174 | BN37: =SUMIFS($B37:$BI37,$B$4:$BI$4,"<=48",$B$4:$BI$4,">36") -> 74186338 | BO37: =SUMIFS($B37:$BI37,$B$4:$BI$4,"<=60",$B$4:$BI$4,">48") -> 1.2084658e+08
BJ38: =A38 -> 0
A39: ='Assumption Table'!B33 -> 4. Advertisement | BJ39: =A39 -> 4. Advertisement
A40: Impressions | B40: =ROUND(MAX(0,NORMINV(RAND(),'Assumption Table'!$C$35,'Assumption Table'!$C$36)),0) -> 10079 | C40: =ROUND(MAX(0,NORMINV(RAND(),'Assumption Table'!$C$35,'Assumption Table'!$C$36)),0) -> 11067 | D40: =ROUND(MAX(0,NORMINV(RAND(),'Assumption Table'!$C$35,'Assumption Table'!$C$36)),0) -> 11537 | E40: =ROUND(MAX(0,NORMINV(RAND(),'Assumption Table'!$C$35,'Assumption Table'!$C$36)),0) -> 10424 | F40: =ROUND(MAX(0,NORMINV(RAND(),'Assumption Table'!$C$35,'Assumption Table'!$C$36)),0) -> 11173 | G40: =ROUND(MAX(0,NORMINV(RAND(),'Assumption Table'!$C$35,'Assumption Table'!$C$36)),0) -> 8244 | H40: =ROUND(MAX(0,NORMINV(RAND(),'Assumption Table'!$C$35,'Assumption Table'!$C$36)),0) -> 10918 | I40: =ROUND(MAX(0,NORMINV(RAND(),'Assumption Table'!$C$35,'Assumption Table'!$C$36)),0) -> 9396 | ... BI40: =ROUND(MAX(0,NORMINV(RAND(),'Assumption Table'!$C$35,'Assumption Table'!$C$36)),0) -> 10267 | BJ40: =A40 -> Impressions | BK40: =SUMIFS($B40:$BI40,$B$4:$BI$4,"<=12") -> 124553 | BL40: =SUMIFS($B40:$BI40,$B$4:$BI$4,"<=24",$B$4:$BI$4,">12") -> 121258 | BM40: =SUMIFS($B40:$BI40,$B$4:$BI$4,"<=36",$B$4:$BI$4,">24") -> 118345 | BN40: =SUMIFS($B40:$BI40,$B$4:$BI$4,"<=48",$B$4:$BI$4,">36") -> 120534 | BO40: =SUMIFS($B40:$BI40,$B$4:$BI$4,"<=60",$B$4:$BI$4,">48") -> 114405
A41: CTR | B41: =MAX(0,MIN(1,NORMINV(RAND(),'Assumption Table'!$C$38,'Assumption Table'!$C$39))) -> 0.2473608 | C41: =MAX(0,MIN(1,NORMINV(RAND(),'Assumption Table'!$C$38,'Assumption Table'!$C$39))) -> 0.24990149 | D41: =MAX(0,MIN(1,NORMINV(RAND(),'Assumption Table'!$C$38,'Assumption Table'!$C$39))) -> 0.23942449 | E41: =MAX(0,MIN(1,NORMINV(RAND(),'Assumption Table'!$C$38,'Assumption Table'!$C$39))) -> 0.25222841 | F41: =MAX(0,MIN(1,NORMINV(RAND(),'Assumption Table'!$C$38,'Assumption Table'!$C$39))) -> 0.24590516 | G41: =MAX(0,MIN(1,NORMINV(RAND(),'Assumption Table'!$C$38,'Assumption Table'!$C$39))) -> 0.24639794 | H41: =MAX(0,MIN(1,NORMINV(RAND(),'Assumption Table'!$C$38,'Assumption Table'!$C$39))) -> 0.25308281 | I41: =MAX(0,MIN(1,NORMINV(RAND(),'Assumption Table'!$C$38,'Assumption Table'!$C$39))) -> 0.24942222 | ... BI41: =MAX(0,MIN(1,NORMINV(RAND(),'Assumption Table'!$C$38,'Assumption Table'!$C$39))) -> 0.24783989
A42: CPC | B42: ='Assumption Table'!$C$40 -> 0.7 | C42: ='Assumption Table'!$C$40 -> 0.7 | D42: ='Assumption Table'!$C$40 -> 0.7 | E42: ='Assumption Table'!$C$40 -> 0.7 | F42: ='Assumption Table'!$C$40 -> 0.7 | G42: ='Assumption Table'!$C$40 -> 0.7 | H42: ='Assumption Table'!$C$40 -> 0.7 | I42: ='Assumption Table'!$C$40 -> 0.7 | ... BI42: ='Assumption Table'!$C$40 -> 0.7
A43: Total Revenue from Advertisement | B43: =B40*B41*B42 -> 1745.2047 | C43: =C40*C41*C42 -> 1935.9619 | D43: =D40*D41*D42 -> 1933.5683 | E43: =E40*E41*E42 -> 1840.4602 | F43: =F40*F41*F42 -> 1923.2489 | G43: =G40*G41*G42 -> 1421.9132 | H43: =H40*H41*H42 -> 1934.2107 | I43: =I40*I41*I42 -> 1640.4998 | ... BI43: =BI40*BI41*BI42 -> 1781.2005 | BJ43: =A43 -> Total Revenue from Advertisement | BK43: =SUMIFS($B43:$BI43,$B$4:$BI$4,"<=12") -> 21596.568 | BL43: =SUMIFS($B43:$BI43,$B$4:$BI$4,"<=24",$B$4:$BI$4,">12") -> 21329.511 | BM43: =SUMIFS($B43:$BI43,$B$4:$BI$4,"<=36",$B$4:$BI$4,">24") -> 20694.744 | BN43: =SUMIFS($B43:$BI43,$B$4:$BI$4,"<=48",$B$4:$BI$4,">36") -> 21078.407 | BO43: =SUMIFS($B43:$BI43,$B$4:$BI$4,"<=60",$B$4:$BI$4,">48") -> 20060.499
BJ44: =A44 -> 0
A45: ='Assumption Table'!B42 -> 5. Commission | BJ45: =A45 -> 5. Commission
A46: # of Transactions | B46: =ROUND(MAX(0,IF(B47=0,0, NORMINV(RAND(),B47,'Assumption Table'!$C$45))),0) -> 100 | C46: =ROUND(MAX(0,IF(C47=0,0, NORMINV(RAND(),C47,'Assumption Table'!$C$45))),0) -> 105 | D46: =ROUND(MAX(0,IF(D47=0,0, NORMINV(RAND(),D47,'Assumption Table'!$C$45))),0) -> 110 | E46: =ROUND(MAX(0,IF(E47=0,0, NORMINV(RAND(),E47,'Assumption Table'!$C$45))),0) -> 116 | F46: =ROUND(MAX(0,IF(F47=0,0, NORMINV(RAND(),F47,'Assumption Table'!$C$45))),0) -> 121 | G46: =ROUND(MAX(0,IF(G47=0,0, NORMINV(RAND(),G47,'Assumption Table'!$C$45))),0) -> 128 | H46: =ROUND(MAX(0,IF(H47=0,0, NORMINV(RAND(),H47,'Assumption Table'!$C$45))),0) -> 134 | I46: =ROUND(MAX(0,IF(I47=0,0, NORMINV(RAND(),I47,'Assumption Table'!$C$45))),0) -> 141 | ... BI46: =ROUND(MAX(0,IF(BI47=0,0, NORMINV(RAND(),BI47,'Assumption Table'!$C$45))),0) -> 1779 | BJ46: =A46 -> # of Transactions | BK46: =SUMIFS($B46:$BI46,$B$4:$BI$4,"<=12") -> 1592 | BL46: =SUMIFS($B46:$BI46,$B$4:$BI$4,"<=24",$B$4:$BI$4,">12") -> 2859 | BM46: =SUMIFS($B46:$BI46,$B$4:$BI$4,"<=36",$B$4:$BI$4,">24") -> 5134 | BN46: =SUMIFS($B46:$BI46,$B$4:$BI$4,"<=48",$B$4:$BI$4,">36") -> 9219 | BO46: =SUMIFS($B46:$BI46,$B$4:$BI$4,"<=60",$B$4:$BI$4,">48") -> 16557
A47: Mean | B47: ='Assumption Table'!$C$44*(1+'Assumption Table'!$C$46)^(B17-1) -> 100 | C47: ='Assumption Table'!$C$44*(1+'Assumption Table'!$C$46)^(C17-1) -> 105 | D47: ='Assumption Table'!$C$44*(1+'Assumption Table'!$C$46)^(D17-1) -> 110.25 | E47: ='Assumption Table'!$C$44*(1+'Assumption Table'!$C$46)^(E17-1) -> 115.7625 | F47: ='Assumption Table'!$C$44*(1+'Assumption Table'!$C$46)^(F17-1) -> 121.55062 | G47: ='Assumption Table'!$C$44*(1+'Assumption Table'!$C$46)^(G17-1) -> 127.62816 | H47: ='Assumption Table'!$C$44*(1+'Assumption Table'!$C$46)^(H17-1) -> 134.00956 | I47: ='Assumption Table'!$C$44*(1+'Assumption Table'!$C$46)^(I17-1) -> 140.71004 | ... BI47: ='Assumption Table'!$C$44*(1+'Assumption Table'!$C$46)^(BI17-1) -> 1778.9701
A48: Total Revenue from Commission | B48: =B46*'Assumption Table'!$C$47*'Assumption Table'!$C$50 -> 2000 | C48: =C46*'Assumption Table'!$C$47*'Assumption Table'!$C$50 -> 2100 | D48: =D46*'Assumption Table'!$C$47*'Assumption Table'!$C$50 -> 2200 | E48: =E46*'Assumption Table'!$C$47*'Assumption Table'!$C$50 -> 2320 | F48: =F46*'Assumption Table'!$C$47*'Assumption Table'!$C$50 -> 2420 | G48: =G46*'Assumption Table'!$C$47*'Assumption Table'!$C$50 -> 2560 | H48: =H46*'Assumption Table'!$C$47*'Assumption Table'!$C$50 -> 2680 | I48: =I46*'Assumption Table'!$C$47*'Assumption Table'!$C$50 -> 2820 | ... BI48: =BI46*'Assumption Table'!$C$47*'Assumption Table'!$C$50 -> 35580 | BJ48: =A48 -> Total Revenue from Commission | BK48: =SUMIFS($B48:$BI48,$B$4:$BI$4,"<=12") -> 31840 | BL48: =SUMIFS($B48:$BI48,$B$4:$BI$4,"<=24",$B$4:$BI$4,">12") -> 57180 | BM48: =SUMIFS($B48:$BI48,$B$4:$BI$4,"<=36",$B$4:$BI$4,">24") -> 102680 | BN48: =SUMIFS($B48:$BI48,$B$4:$BI$4,"<=48",$B$4:$BI$4,">36") -> 184380 | BO48: =SUMIFS($B48:$BI48,$B$4:$BI$4,"<=60",$B$4:$BI$4,">48") -> 331140
BJ49: =A49 -> 0
BJ50: =A50 -> 0
A51: Total Revenue | B51: =SUM(B19,B26,B37,B43,B48) -> 182085.63 | C51: =SUM(C19,C26,C37,C43,C48) -> 351864.55 | D51: =SUM(D19,D26,D37,D43,D48) -> 687132.49 | E51: =SUM(E19,E26,E37,E43,E48) -> 482439.62 | F51: =SUM(F19,F26,F37,F43,F48) -> 647516.93 | G51: =SUM(G19,G26,G37,G43,G48) -> 1109791.1 | H51: =SUM(H19,H26,H37,H43,H48) -> 1068888.1 | I51: =SUM(I19,I26,I37,I43,I48) -> 1494151.5 | ... BI51: =SUM(BI19,BI26,BI37,BI43,BI48) -> 19172062 | BJ51: =A51 -> Total Revenue | BK51: =SUMIFS($B51:$BI51,$B$4:$BI$4,"<=12") -> 13373368 | BL51: =SUMIFS($B51:$BI51,$B$4:$BI$4,"<=24",$B$4:$BI$4,">12") -> 43180301 | BM51: =SUMIFS($B51:$BI51,$B$4:$BI$4,"<=36",$B$4:$BI$4,">24") -> 75809230 | BN51: =SUMIFS($B51:$BI51,$B$4:$BI$4,"<=48",$B$4:$BI$4,">36") -> 1.0939626e+08 | BO51: =SUMIFS($B51:$BI51,$B$4:$BI$4,"<=60",$B$4:$BI$4,">48") -> 1.7643694e+08
BJ52: =A52 -> 0
A53: Cost of Goods Sold Schedule | BJ53: =A53 -> Cost of Goods Sold Schedule
B54: 1 | C54: 2 | D54: 3 | E54: 4 | F54: 5 | G54: 6 | H54: 7 | I54: 8 | J54: 9 | K54: 10 | L54: 11 | M54: 12 | N54: 13 | O54: 14 | P54: 15 | Q54: 16 | R54: 17 | S54: 18 | T54: 19 | U54: 20 | V54: 21 | W54: 22 | X54: 23 | Y54: 24 | Z54: 25 | AA54: 26 | AB54: 27 | AC54: 28 | AD54: 29 | AE54: 30 | AF54: 31 | AG54: 32 | AH54: 33 | AI54: 34 | AJ54: 35 | AK54: 36 | AL54: 37 | AM54: 38 | AN54: 39 | AO54: 40 | AP54: 41 | AQ54: 42 | AR54: 43 | AS54: 44 | AT54: 45 | AU54: 46 | AV54: 47 | AW54: 48 | AX54: 49 | AY54: 50 | AZ54: 51 | BA54: 52 | BB54: 53 | BC54: 54 | BD54: 55 | BE54: 56 | BF54: 57 | BG54: 58 | BH54: 59 | BI54: 60 | BJ54: =A54 -> 0 | BK54: 1 | BL54: 2 | BM54: 3 | BN54: 4 | BO54: 5
A55: Hosting and Infrastructure | B55: =B51*'Assumption Table'!$C$55 -> 5462.5689 | C55: =C51*'Assumption Table'!$C$55 -> 10555.937 | D55: =D51*'Assumption Table'!$C$55 -> 20613.975 | E55: =E51*'Assumption Table'!$C$55 -> 14473.189 | F55: =F51*'Assumption Table'!$C$55 -> 19425.508 | G55: =G51*'Assumption Table'!$C$55 -> 33293.733 | H55: =H51*'Assumption Table'!$C$55 -> 32066.644 | I55: =I51*'Assumption Table'!$C$55 -> 44824.546 | ... BI55: =BI51*'Assumption Table'!$C$55 -> 575161.87 | BJ55: =A55 -> Hosting and Infrastructure | BK55: =SUMIFS($B55:$BI55,$B$4:$BI$4,"<=12") -> 401201.05 | BL55: =SUMIFS($B55:$BI55,$B$4:$BI$4,"<=24",$B$4:$BI$4,">12") -> 1295409 | BM55: =SUMIFS($B55:$BI55,$B$4:$BI$4,"<=36",$B$4:$BI$4,">24") -> 2274276.9 | BN55: =SUMIFS($B55:$BI55,$B$4:$BI$4,"<=48",$B$4:$BI$4,">36") -> 3281887.7 | BO55: =SUMIFS($B55:$BI55,$B$4:$BI$4,"<=60",$B$4:$BI$4,">48") -> 5293108.2
A56: Development and Maintenance | B56: =B51*'Assumption Table'!$C$56 -> 27312.845 | C56: =C51*'Assumption Table'!$C$56 -> 52779.683 | D56: =D51*'Assumption Table'!$C$56 -> 103069.87 | E56: =E51*'Assumption Table'!$C$56 -> 72365.943 | F56: =F51*'Assumption Table'!$C$56 -> 97127.54 | G56: =G51*'Assumption Table'!$C$56 -> 166468.67 | H56: =H51*'Assumption Table'!$C$56 -> 160333.22 | I56: =I51*'Assumption Table'!$C$56 -> 224122.73 | ... BI56: =BI51*'Assumption Table'!$C$56 -> 2875809.3 | BJ56: =A56 -> Development and Maintenance | BK56: =SUMIFS($B56:$BI56,$B$4:$BI$4,"<=12") -> 2006005.3 | BL56: =SUMIFS($B56:$BI56,$B$4:$BI$4,"<=24",$B$4:$BI$4,">12") -> 6477045.2 | BM56: =SUMIFS($B56:$BI56,$B$4:$BI$4,"<=36",$B$4:$BI$4,">24") -> 11371385 | BN56: =SUMIFS($B56:$BI56,$B$4:$BI$4,"<=48",$B$4:$BI$4,">36") -> 16409439 | BO56: =SUMIFS($B56:$BI56,$B$4:$BI$4,"<=60",$B$4:$BI$4,">48") -> 26465541
A57: Customer Support | B57: =ROUND(B14/'Assumption Table'!$C$58,0)*'Assumption Table'!$C$59 -> 30000 | C57: =ROUND(C14/'Assumption Table'!$C$58,0)*'Assumption Table'!$C$59 -> 68000 | D57: =ROUND(D14/'Assumption Table'!$C$58,0)*'Assumption Table'!$C$59 -> 106000 | E57: =ROUND(E14/'Assumption Table'!$C$58,0)*'Assumption Table'!$C$59 -> 102000 | F57: =ROUND(F14/'Assumption Table'!$C$58,0)*'Assumption Table'!$C$59 -> 168000 | G57: =ROUND(G14/'Assumption Table'!$C$58,0)*'Assumption Table'!$C$59 -> 192000 | H57: =ROUND(H14/'Assumption Table'!$C$58,0)*'Assumption Table'!$C$59 -> 216000 | I57: =ROUND(I14/'Assumption Table'!$C$58,0)*'Assumption Table'!$C$59 -> 266000 | ... BI57: =ROUND(BI14/'Assumption Table'!$C$58,0)*'Assumption Table'!$C$59 -> 3892000 | BJ57: =A57 -> Customer Support | BK57: =SUMIFS($B57:$BI57,$B$4:$BI$4,"<=12") -> 2494000 | BL57: =SUMIFS($B57:$BI57,$B$4:$BI$4,"<=24",$B$4:$BI$4,">12") -> 8410000 | BM57: =SUMIFS($B57:$BI57,$B$4:$BI$4,"<=36",$B$4:$BI$4,">24") -> 14910000 | BN57: =SUMIFS($B57:$BI57,$B$4:$BI$4,"<=48",$B$4:$BI$4,">36") -> 23896000 | BO57: =SUMIFS($B57:$BI57,$B$4:$BI$4,"<=60",$B$4:$BI$4,">48") -> 35764000
A58: Content Licensing | B58: =B51*'Assumption Table'!$C$60 -> 1820.8563 | C58: =C51*'Assumption Table'!$C$60 -> 3518.6455 | D58: =D51*'Assumption Table'!$C$60 -> 6871.3249 | E58: =E51*'Assumption Table'!$C$60 -> 4824.3962 | F58: =F51*'Assumption Table'!$C$60 -> 6475.1693 | G58: =G51*'Assumption Table'!$C$60 -> 11097.911 | H58: =H51*'Assumption Table'!$C$60 -> 10688.881 | I58: =I51*'Assumption Table'!$C$60 -> 14941.515 | ... BI58: =BI51*'Assumption Table'!$C$60 -> 191720.62 | BJ58: =A58 -> Content Licensing | BK58: =SUMIFS($B58:$BI58,$B$4:$BI$4,"<=12") -> 133733.68 | BL58: =SUMIFS($B58:$BI58,$B$4:$BI$4,"<=24",$B$4:$BI$4,">12") -> 431803.01 | BM58: =SUMIFS($B58:$BI58,$B$4:$BI$4,"<=36",$B$4:$BI$4,">24") -> 758092.3 | BN58: =SUMIFS($B58:$BI58,$B$4:$BI$4,"<=48",$B$4:$BI$4,">36") -> 1093962.6 | BO58: =SUMIFS($B58:$BI58,$B$4:$BI$4,"<=60",$B$4:$BI$4,">48") -> 1764369.4
A59: Payment Processing | B59: =B51*'Assumption Table'!$D$67 -> 2336.1586 | C59: =C51*'Assumption Table'!$D$67 -> 4514.4222 | D59: =D51*'Assumption Table'!$D$67 -> 8815.9099 | E59: =E51*'Assumption Table'!$D$67 -> 6189.7003 | F59: =F51*'Assumption Table'!$D$67 -> 8307.6423 | G59: =G51*'Assumption Table'!$D$67 -> 14238.62 | H59: =H51*'Assumption Table'!$D$67 -> 13713.835 | I59: =I51*'Assumption Table'!$D$67 -> 19169.964 | ... BI59: =BI51*'Assumption Table'!$D$67 -> 245977.56 | BJ59: =A59 -> Payment Processing | BK59: =SUMIFS($B59:$BI59,$B$4:$BI$4,"<=12") -> 171580.32 | BL59: =SUMIFS($B59:$BI59,$B$4:$BI$4,"<=24",$B$4:$BI$4,">12") -> 554003.26 | BM59: =SUMIFS($B59:$BI59,$B$4:$BI$4,"<=36",$B$4:$BI$4,">24") -> 972632.42 | BN59: =SUMIFS($B59:$BI59,$B$4:$BI$4,"<=48",$B$4:$BI$4,">36") -> 1403554 | BO59: =SUMIFS($B59:$BI59,$B$4:$BI$4,"<=60",$B$4:$BI$4,">48") -> 2263685.9
A60: Platform Fees | B60: =B51*'Assumption Table'!$C$61 -> 54625.689 | C60: =C51*'Assumption Table'!$C$61 -> 105559.37 | D60: =D51*'Assumption Table'!$C$61 -> 206139.75 | E60: =E51*'Assumption Table'!$C$61 -> 144731.89 | F60: =F51*'Assumption Table'!$C$61 -> 194255.08 | G60: =G51*'Assumption Table'!$C$61 -> 332937.33 | H60: =H51*'Assumption Table'!$C$61 -> 320666.44 | I60: =I51*'Assumption Table'!$C$61 -> 448245.46 | ... BI60: =BI51*'Assumption Table'!$C$61 -> 5751618.7 | BJ60: =A60 -> Platform Fees | BK60: =SUMIFS($B60:$BI60,$B$4:$BI$4,"<=12") -> 4012010.5 | BL60: =SUMIFS($B60:$BI60,$B$4:$BI$4,"<=24",$B$4:$BI$4,">12") -> 12954090 | BM60: =SUMIFS($B60:$BI60,$B$4:$BI$4,"<=36",$B$4:$BI$4,">24") -> 22742769 | BN60: =SUMIFS($B60:$BI60,$B$4:$BI$4,"<=48",$B$4:$BI$4,">36") -> 32818877 | BO60: =SUMIFS($B60:$BI60,$B$4:$BI$4,"<=60",$B$4:$BI$4,">48") -> 52931082
A62: Gross Margin Rate | B62: =(B51-B63)/B51 -> 0.36241235 | C62: =(C51-C63)/C51 -> 0.33391382 | D62: =(D51-D63)/D51 -> 0.37290572 | E62: =(E51-E63)/E51 -> 0.31574458 | F62: =(F51-F63)/F51 -> 0.26771733 | G62: =(G51-G63)/G51 -> 0.35416447 | H62: =(H51-H63)/H51 -> 0.32509086 | I62: =(I51-I63)/I51 -> 0.34914254 | ... BI62: =(BI51-BI63)/BI51 -> 0.32416628 | BJ62: =A62 -> Gross Margin Rate | BK62: =(BK51-BK63)/BK51 -> 0.34067996 | BL62: =(BL51-BL63)/BL51 -> 0.33240526 | BM62: =(BM51-BM63)/BM51 -> 0.3304921 | BN62: =(BN51-BN63)/BN51 -> 0.30873474 | BO62: =(BO51-BO63)/BO51 -> 0.32446868
A63: Total COGS | B63: =SUM(B56:B60) -> 116095.55 | C63: =SUM(C56:C60) -> 234372.12 | D63: =SUM(D56:D60) -> 430896.86 | E63: =SUM(E56:E60) -> 330111.93 | F63: =SUM(F56:F60) -> 474165.43 | G63: =SUM(G56:G60) -> 716742.53 | H63: =SUM(H56:H60) -> 721402.38 | I63: =SUM(I56:I60) -> 972479.67 | ... BI63: =SUM(BI56:BI60) -> 12957126 | BJ63: =A63 -> Total COGS | BK63: =SUMIFS($B63:$BI63,$B$4:$BI$4,"<=12") -> 8817329.8 | BL63: =SUMIFS($B63:$BI63,$B$4:$BI$4,"<=24",$B$4:$BI$4,">12") -> 28826942 | BM63: =SUMIFS($B63:$BI63,$B$4:$BI$4,"<=36",$B$4:$BI$4,">24") -> 50754878 | BN63: =SUMIFS($B63:$BI63,$B$4:$BI$4,"<=48",$B$4:$BI$4,">36") -> 75621832 | BO63: =SUMIFS($B63:$BI63,$B$4:$BI$4,"<=60",$B$4:$BI$4,">48") -> 1.1918868e+08
A64: Consolidated Operating Expenses Schedule | BJ64: =A64 -> Consolidated Operating Expenses Schedule
B65: 1 | C65: 2 | D65: 3 | E65: 4 | F65: 5 | G65: 6 | H65: 7 | I65: 8 | J65: 9 | K65: 10 | L65: 11 | M65: 12 | N65: 13 | O65: 14 | P65: 15 | Q65: 16 | R65: 17 | S65: 18 | T65: 19 | U65: 20 | V65: 21 | W65: 22 | X65: 23 | Y65: 24 | Z65: 25 | AA65: 26 | AB65: 27 | AC65: 28 | AD65: 29 | AE65: 30 | AF65: 31 | AG65: 32 | AH65: 33 | AI65: 34 | AJ65: 35 | AK65: 36 | AL65: 37 | AM65: 38 | AN65: 39 | AO65: 40 | AP65: 41 | AQ65: 42 | AR65: 43 | AS65: 44 | AT65: 45 | AU65: 46 | AV65: 47 | AW65: 48 | AX65: 49 | AY65: 50 | AZ65: 51 | BA65: 52 | BB65: 53 | BC65: 54 | BD65: 55 | BE65: 56 | BF65: 57 | BG65: 58 | BH65: 59 | BI65: 60 | BJ65: =A65 -> 0 | BK65: 1 | BL65: 2 | BM65: 3 | BN65: 4 | BO65: 5
A66: Research & Development expense per month | B66: ='Assumption Table'!$C$70 -> 650 | C66: ='Assumption Table'!$C$70 -> 650 | D66: ='Assumption Table'!$C$70 -> 650 | E66: ='Assumption Table'!$C$70 -> 650 | F66: ='Assumption Table'!$C$70 -> 650 | G66: ='Assumption Table'!$C$70 -> 650 | H66: ='Assumption Table'!$C$70 -> 650 | I66: ='Assumption Table'!$C$70 -> 650 | ... BI66: ='Assumption Table'!$C$70 -> 650 | BJ66: Research & Development expense per year | BK66: =SUMIFS($B66:$BI66,$B$4:$BI$4,"<=12") -> 7800 | BL66: =SUMIFS($B66:$BI66,$B$4:$BI$4,"<=24",$B$4:$BI$4,">12") -> 7800 | BM66: =SUMIFS($B66:$BI66,$B$4:$BI$4,"<=36",$B$4:$BI$4,">24") -> 7800 | BN66: =SUMIFS($B66:$BI66,$B$4:$BI$4,"<=48",$B$4:$BI$4,">36") -> 7800 | BO66: =SUMIFS($B66:$BI66,$B$4:$BI$4,"<=60",$B$4:$BI$4,">48") -> 7800
A67: General & Admin expense | B67: =B51*'Assumption Table'!$C$71 -> 9104.2816 | C67: =C51*'Assumption Table'!$C$71 -> 17593.228 | D67: =D51*'Assumption Table'!$C$71 -> 34356.625 | E67: =E51*'Assumption Table'!$C$71 -> 24121.981 | F67: =F51*'Assumption Table'!$C$71 -> 32375.847 | G67: =G51*'Assumption Table'!$C$71 -> 55489.555 | H67: =H51*'Assumption Table'!$C$71 -> 53444.407 | I67: =I51*'Assumption Table'!$C$71 -> 74707.576 | ... BI67: =BI51*'Assumption Table'!$C$71 -> 958603.11 | BJ67: =A67 -> General & Admin expense | BK67: =SUMIFS($B67:$BI67,$B$4:$BI$4,"<=12") -> 668668.42 | BL67: =SUMIFS($B67:$BI67,$B$4:$BI$4,"<=24",$B$4:$BI$4,">12") -> 2159015.1 | BM67: =SUMIFS($B67:$BI67,$B$4:$BI$4,"<=36",$B$4:$BI$4,">24") -> 3790461.5 | BN67: =SUMIFS($B67:$BI67,$B$4:$BI$4,"<=48",$B$4:$BI$4,">36") -> 5469812.8 | BO67: =SUMIFS($B67:$BI67,$B$4:$BI$4,"<=60",$B$4:$BI$4,">48") -> 8821847
A68: Office Space | B68: =_xludf.ifs(B4<=12,$BK$68/12,B4<=24,$BL$68/12,B4<=36,$BM$68/12,B4<=48,$BN$68/12,B4<=60,$BO$68/12) -> #NAME? | C68: =_xludf.ifs(C4<=12,$BK$68/12,C4<=24,$BL$68/12,C4<=36,$BM$68/12,C4<=48,$BN$68/12,C4<=60,$BO$68/12) -> #NAME? | D68: =_xludf.ifs(D4<=12,$BK$68/12,D4<=24,$BL$68/12,D4<=36,$BM$68/12,D4<=48,$BN$68/12,D4<=60,$BO$68/12) -> #NAME? | E68: =_xludf.ifs(E4<=12,$BK$68/12,E4<=24,$BL$68/12,E4<=36,$BM$68/12,E4<=48,$BN$68/12,E4<=60,$BO$68/12) -> #NAME? | F68: =_xludf.ifs(F4<=12,$BK$68/12,F4<=24,$BL$68/12,F4<=36,$BM$68/12,F4<=48,$BN$68/12,F4<=60,$BO$68/12) -> #NAME? | G68: =_xludf.ifs(G4<=12,$BK$68/12,G4<=24,$BL$68/12,G4<=36,$BM$68/12,G4<=48,$BN$68/12,G4<=60,$BO$68/12) -> #NAME? | H68: =_xludf.ifs(H4<=12,$BK$68/12,H4<=24,$BL$68/12,H4<=36,$BM$68/12,H4<=48,$BN$68/12,H4<=60,$BO$68/12) -> #NAME? | I68: =_xludf.ifs(I4<=12,$BK$68/12,I4<=24,$BL$68/12,I4<=36,$BM$68/12,I4<=48,$BN$68/12,I4<=60,$BO$68/12) -> #NAME? | ... BI68: =_xludf.ifs(BI4<=12,$BK$68/12,BI4<=24,$BL$68/12,BI4<=36,$BM$68/12,BI4<=48,$BN$68/12,BI4<=60,$BO$68/12) -> #NAME? | BJ68: =A68 -> Office Space | BK68: ='Assumption Table'!$C$72*12*(1+'Assumption Table'!$C$73)^(BK4-1) -> 120000 | BL68: ='Assumption Table'!$C$72*12*(1+'Assumption Table'!$C$73)^(BL4-1) -> 122400 | BM68: ='Assumption Table'!$C$72*12*(1+'Assumption Table'!$C$73)^(BM4-1) -> 124848 | BN68: ='Assumption Table'!$C$72*12*(1+'Assumption Table'!$C$73)^(BN4-1) -> 127344.96 | BO68: ='Assumption Table'!$C$72*12*(1+'Assumption Table'!$C$73)^(BO4-1) -> 129891.86
A69: Sales & Marketing | B69: =B70+B71 -> 10017 | C69: =C70+C71 -> 9922 | D69: =D70+D71 -> 10195 | E69: =E70+E71 -> 10210 | F69: =F70+F71 -> 10384 | G69: =G70+G71 -> 10426 | H69: =H70+H71 -> 10545 | I69: =I70+I71 -> 10740 | ... BI69: =BI70+BI71 -> 21135 | BJ69: =A69 -> Sales & Marketing
A70: Fixed Cost | B70: ='Assumption Table'!$C$75 -> 5000 | C70: ='Assumption Table'!$C$75 -> 5000 | D70: ='Assumption Table'!$C$75 -> 5000 | E70: ='Assumption Table'!$C$75 -> 5000 | F70: ='Assumption Table'!$C$75 -> 5000 | G70: ='Assumption Table'!$C$75 -> 5000 | H70: ='Assumption Table'!$C$75 -> 5000 | I70: ='Assumption Table'!$C$75 -> 5000 | ... BI70: ='Assumption Table'!$C$75 -> 5000 | BJ70: =A70 -> Fixed Cost | BK70: =SUMIFS($B70:$BI70,$B$4:$BI$4,"<=12") -> 60000 | BL70: =SUMIFS($B70:$BI70,$B$4:$BI$4,"<=24",$B$4:$BI$4,">12") -> 60000 | BM70: =SUMIFS($B70:$BI70,$B$4:$BI$4,"<=36",$B$4:$BI$4,">24") -> 60000 | BN70: =SUMIFS($B70:$BI70,$B$4:$BI$4,"<=48",$B$4:$BI$4,">36") -> 60000 | BO70: =SUMIFS($B70:$BI70,$B$4:$BI$4,"<=60",$B$4:$BI$4,">48") -> 60000
A71: Variable Cost | B71: =B7*'Assumption Table'!$C$76 -> 5017 | C71: =C7*'Assumption Table'!$C$76 -> 4922 | D71: =D7*'Assumption Table'!$C$76 -> 5195 | E71: =E7*'Assumption Table'!$C$76 -> 5210 | F71: =F7*'Assumption Table'!$C$76 -> 5384 | G71: =G7*'Assumption Table'!$C$76 -> 5426 | H71: =H7*'Assumption Table'!$C$76 -> 5545 | I71: =I7*'Assumption Table'!$C$76 -> 5740 | ... BI71: =BI7*'Assumption Table'!$C$76 -> 16135 | BJ71: =A71 -> Variable Cost | BK71: =SUMIFS($B71:$BI71,$B$4:$BI$4,"<=12") -> 66699 | BL71: =SUMIFS($B71:$BI71,$B$4:$BI$4,"<=24",$B$4:$BI$4,">12") -> 85321 | BM71: =SUMIFS($B71:$BI71,$B$4:$BI$4,"<=36",$B$4:$BI$4,">24") -> 108341 | BN71: =SUMIFS($B71:$BI71,$B$4:$BI$4,"<=48",$B$4:$BI$4,">36") -> 136488 | BO71: =SUMIFS($B71:$BI71,$B$4:$BI$4,"<=60",$B$4:$BI$4,">48") -> 173450
A72: Technology and Infrastructure | B72: =B51*'Assumption Table'!$C$77 -> 18208.563 | C72: =C51*'Assumption Table'!$C$77 -> 35186.455 | D72: =D51*'Assumption Table'!$C$77 -> 68713.249 | E72: =E51*'Assumption Table'!$C$77 -> 48243.962 | F72: =F51*'Assumption Table'!$C$77 -> 64751.693 | G72: =G51*'Assumption Table'!$C$77 -> 110979.11 | H72: =H51*'Assumption Table'!$C$77 -> 106888.81 | I72: =I51*'Assumption Table'!$C$77 -> 149415.15 | ... BI72: =BI51*'Assumption Table'!$C$77 -> 1917206.2 | BJ72: =A72 -> Technology and Infrastructure | BK72: =SUMIFS($B72:$BI72,$B$4:$BI$4,"<=12") -> 1337336.8 | BL72: =SUMIFS($B72:$BI72,$B$4:$BI$4,"<=24",$B$4:$BI$4,">12") -> 4318030.1 | BM72: =SUMIFS($B72:$BI72,$B$4:$BI$4,"<=36",$B$4:$BI$4,">24") -> 7580923 | BN72: =SUMIFS($B72:$BI72,$B$4:$BI$4,"<=48",$B$4:$BI$4,">36") -> 10939626 | BO72: =SUMIFS($B72:$BI72,$B$4:$BI$4,"<=60",$B$4:$BI$4,">48") -> 17643694
A73: Other Operating Expenses | B73: =B51*'Assumption Table'!$C$78 -> 1820.8563 | C73: =C51*'Assumption Table'!$C$78 -> 3518.6455 | D73: =D51*'Assumption Table'!$C$78 -> 6871.3249 | E73: =E51*'Assumption Table'!$C$78 -> 4824.3962 | F73: =F51*'Assumption Table'!$C$78 -> 6475.1693 | G73: =G51*'Assumption Table'!$C$78 -> 11097.911 | H73: =H51*'Assumption Table'!$C$78 -> 10688.881 | I73: =I51*'Assumption Table'!$C$78 -> 14941.515 | ... BI73: =BI51*'Assumption Table'!$C$78 -> 191720.62 | BJ73: =A73 -> Other Operating Expenses | BK73: =SUMIFS($B73:$BI73,$B$4:$BI$4,"<=12") -> 133733.68 | BL73: =SUMIFS($B73:$BI73,$B$4:$BI$4,"<=24",$B$4:$BI$4,">12") -> 431803.01 | BM73: =SUMIFS($B73:$BI73,$B$4:$BI$4,"<=36",$B$4:$BI$4,">24") -> 758092.3 | BN73: =SUMIFS($B73:$BI73,$B$4:$BI$4,"<=48",$B$4:$BI$4,">36") -> 1093962.6 | BO73: =SUMIFS($B73:$BI73,$B$4:$BI$4,"<=60",$B$4:$BI$4,">48") -> 1764369.4
BJ74: =A74 -> 0
A75: Total Monthly Expenses | B75: =SUM(B66:B73) -> #NAME? | C75: =SUM(C66:C73) -> #NAME? | D75: =SUM(D66:D73) -> #NAME? | E75: =SUM(E66:E73) -> #NAME? | F75: =SUM(F66:F73) -> #NAME? | G75: =SUM(G66:G73) -> #NAME? | H75: =SUM(H66:H73) -> #NAME? | I75: =SUM(I66:I73) -> #NAME? | ... BI75: =SUM(BI66:BI73) -> #NAME? | BJ75: =A75 -> Total Monthly Expenses | BK75: =SUMIFS($B75:$BI75,$B$4:$BI$4,"<=12") -> #NAME? | BL75: =SUMIFS($B75:$BI75,$B$4:$BI$4,"<=24",$B$4:$BI$4,">12") -> #NAME? | BM75: =SUMIFS($B75:$BI75,$B$4:$BI$4,"<=36",$B$4:$BI$4,">24") -> #NAME? | BN75: =SUMIFS($B75:$BI75,$B$4:$BI$4,"<=48",$B$4:$BI$4,">36") -> #NAME? | BO75: =SUMIFS($B75:$BI75,$B$4:$BI$4,"<=60",$B$4:$BI$4,">48") -> #NAME?
BJ76: =A76 -> 0
A77: Capital Expenditure Projection | BJ77: =A77 -> Capital Expenditure Projection
BJ78: =A78 -> 0
B79: 1 | C79: 2 | D79: 3 | E79: 4 | F79: 5 | G79: 6 | H79: 7 | I79: 8 | J79: 9 | K79: 10 | L79: 11 | M79: 12 | N79: 13 | O79: 14 | P79: 15 | Q79: 16 | R79: 17 | S79: 18 | T79: 19 | U79: 20 | V79: 21 | W79: 22 | X79: 23 | Y79: 24 | Z79: 25 | AA79: 26 | AB79: 27 | AC79: 28 | AD79: 29 | AE79: 30 | AF79: 31 | AG79: 32 | AH79: 33 | AI79: 34 | AJ79: 35 | AK79: 36 | AL79: 37 | AM79: 38 | AN79: 39 | AO79: 40 | AP79: 41 | AQ79: 42 | AR79: 43 | AS79: 44 | AT79: 45 | AU79: 46 | AV79: 47 | AW79: 48 | AX79: 49 | AY79: 50 | AZ79: 51 | BA79: 52 | BB79: 53 | BC79: 54 | BD79: 55 | BE79: 56 | BF79: 57 | BG79: 58 | BH79: 59 | BI79: 60 | BJ79: =A79 -> 0 | BK79: 1 | BL79: 2 | BM79: 3 | BN79: 4 | BO79: 5
A80: Technology Infrastructure | BJ80: =A80 -> Technology Infrastructure
A81: Servers and Data Centers | B81: =VLOOKUP($A81,'Assumption Table'!$B$83:$D$101,3,FALSE)*B$51 -> 5462.5689 | C81: =VLOOKUP($A81,'Assumption Table'!$B$83:$D$101,3,FALSE)*C$51 -> 10555.937 | D81: =VLOOKUP($A81,'Assumption Table'!$B$83:$D$101,3,FALSE)*D$51 -> 20613.975 | E81: =VLOOKUP($A81,'Assumption Table'!$B$83:$D$101,3,FALSE)*E$51 -> 14473.189 | F81: =VLOOKUP($A81,'Assumption Table'!$B$83:$D$101,3,FALSE)*F$51 -> 19425.508 | G81: =VLOOKUP($A81,'Assumption Table'!$B$83:$D$101,3,FALSE)*G$51 -> 33293.733 | H81: =VLOOKUP($A81,'Assumption Table'!$B$83:$D$101,3,FALSE)*H$51 -> 32066.644 | I81: =VLOOKUP($A81,'Assumption Table'!$B$83:$D$101,3,FALSE)*I$51 -> 44824.546 | ... BI81: =VLOOKUP($A81,'Assumption Table'!$B$83:$D$101,3,FALSE)*BI$51 -> 575161.87 | BJ81: =A81 -> Servers and Data Centers | BK81: =SUMIFS($B81:$BI81,$B$4:$BI$4,"<=12") -> 401201.05 | BL81: =SUMIFS($B81:$BI81,$B$4:$BI$4,"<=24",$B$4:$BI$4,">12") -> 1295409 | BM81: =SUMIFS($B81:$BI81,$B$4:$BI$4,"<=36",$B$4:$BI$4,">24") -> 2274276.9 | BN81: =SUMIFS($B81:$BI81,$B$4:$BI$4,"<=48",$B$4:$BI$4,">36") -> 3281887.7 | BO81: =SUMIFS($B81:$BI81,$B$4:$BI$4,"<=60",$B$4:$BI$4,">48") -> 5293108.2
A82: Networking Equipment | B82: =VLOOKUP($A82,'Assumption Table'!$B$83:$D$101,3,FALSE)*B$51 -> 1820.8563 | C82: =VLOOKUP($A82,'Assumption Table'!$B$83:$D$101,3,FALSE)*C$51 -> 3518.6455 | D82: =VLOOKUP($A82,'Assumption Table'!$B$83:$D$101,3,FALSE)*D$51 -> 6871.3249 | E82: =VLOOKUP($A82,'Assumption Table'!$B$83:$D$101,3,FALSE)*E$51 -> 4824.3962 | F82: =VLOOKUP($A82,'Assumption Table'!$B$83:$D$101,3,FALSE)*F$51 -> 6475.1693 | G82: =VLOOKUP($A82,'Assumption Table'!$B$83:$D$101,3,FALSE)*G$51 -> 11097.911 | H82: =VLOOKUP($A82,'Assumption Table'!$B$83:$D$101,3,FALSE)*H$51 -> 10688.881 | I82: =VLOOKUP($A82,'Assumption Table'!$B$83:$D$101,3,FALSE)*I$51 -> 14941.515 | ... BI82: =VLOOKUP($A82,'Assumption Table'!$B$83:$D$101,3,FALSE)*BI$51 -> 191720.62 | BJ82: =A82 -> Networking Equipment | BK82: =SUMIFS($B82:$BI82,$B$4:$BI$4,"<=12") -> 133733.68 | BL82: =SUMIFS($B82:$BI82,$B$4:$BI$4,"<=24",$B$4:$BI$4,">12") -> 431803.01 | BM82: =SUMIFS($B82:$BI82,$B$4:$BI$4,"<=36",$B$4:$BI$4,">24") -> 758092.3 | BN82: =SUMIFS($B82:$BI82,$B$4:$BI$4,"<=48",$B$4:$BI$4,">36") -> 1093962.6 | BO82: =SUMIFS($B82:$BI82,$B$4:$BI$4,"<=60",$B$4:$BI$4,">48") -> 1764369.4
A83: Software and Licenses | BJ83: =A83 -> Software and Licenses
A84: Enterprise Software | B84: =VLOOKUP($A84,'Assumption Table'!$B$83:$D$101,3,FALSE)*B$51 -> 3641.7126 | C84: =VLOOKUP($A84,'Assumption Table'!$B$83:$D$101,3,FALSE)*C$51 -> 7037.2911 | D84: =VLOOKUP($A84,'Assumption Table'!$B$83:$D$101,3,FALSE)*D$51 -> 13742.65 | E84: =VLOOKUP($A84,'Assumption Table'!$B$83:$D$101,3,FALSE)*E$51 -> 9648.7924 | F84: =VLOOKUP($A84,'Assumption Table'!$B$83:$D$101,3,FALSE)*F$51 -> 12950.339 | G84: =VLOOKUP($A84,'Assumption Table'!$B$83:$D$101,3,FALSE)*G$51 -> 22195.822 | H84: =VLOOKUP($A84,'Assumption Table'!$B$83:$D$101,3,FALSE)*H$51 -> 21377.763 | I84: =VLOOKUP($A84,'Assumption Table'!$B$83:$D$101,3,FALSE)*I$51 -> 29883.031 | ... BI84: =VLOOKUP($A84,'Assumption Table'!$B$83:$D$101,3,FALSE)*BI$51 -> 383441.25 | BJ84: =A84 -> Enterprise Software | BK84: =SUMIFS($B84:$BI84,$B$4:$BI$4,"<=12") -> 267467.37 | BL84: =SUMIFS($B84:$BI84,$B$4:$BI$4,"<=24",$B$4:$BI$4,">12") -> 863606.02 | BM84: =SUMIFS($B84:$BI84,$B$4:$BI$4,"<=36",$B$4:$BI$4,">24") -> 1516184.6 | BN84: =SUMIFS($B84:$BI84,$B$4:$BI$4,"<=48",$B$4:$BI$4,">36") -> 2187925.1 | BO84: =SUMIFS($B84:$BI84,$B$4:$BI$4,"<=60",$B$4:$BI$4,">48") -> 3528738.8
A85: Software Licenses | B85: =VLOOKUP($A85,'Assumption Table'!$B$83:$D$101,3,FALSE)*B$51 -> 1820.8563 | C85: =VLOOKUP($A85,'Assumption Table'!$B$83:$D$101,3,FALSE)*C$51 -> 3518.6455 | D85: =VLOOKUP($A85,'Assumption Table'!$B$83:$D$101,3,FALSE)*D$51 -> 6871.3249 | E85: =VLOOKUP($A85,'Assumption Table'!$B$83:$D$101,3,FALSE)*E$51 -> 4824.3962 | F85: =VLOOKUP($A85,'Assumption Table'!$B$83:$D$101,3,FALSE)*F$51 -> 6475.1693 | G85: =VLOOKUP($A85,'Assumption Table'!$B$83:$D$101,3,FALSE)*G$51 -> 11097.911 | H85: =VLOOKUP($A85,'Assumption Table'!$B$83:$D$101,3,FALSE)*H$51 -> 10688.881 | I85: =VLOOKUP($A85,'Assumption Table'!$B$83:$D$101,3,FALSE)*I$51 -> 14941.515 | ... BI85: =VLOOKUP($A85,'Assumption Table'!$B$83:$D$101,3,FALSE)*BI$51 -> 191720.62 | BJ85: =A85 -> Software Licenses | BK85: =SUMIFS($B85:$BI85,$B$4:$BI$4,"<=12") -> 133733.68 | BL85: =SUMIFS($B85:$BI85,$B$4:$BI$4,"<=24",$B$4:$BI$4,">12") -> 431803.01 | BM85: =SUMIFS($B85:$BI85,$B$4:$BI$4,"<=36",$B$4:$BI$4,">24") -> 758092.3 | BN85: =SUMIFS($B85:$BI85,$B$4:$BI$4,"<=48",$B$4:$BI$4,">36") -> 1093962.6 | BO85: =SUMIFS($B85:$BI85,$B$4:$BI$4,"<=60",$B$4:$BI$4,">48") -> 1764369.4
A86: Hardware | BJ86: =A86 -> Hardware
A87: Computers and Workstations | B87: =VLOOKUP($A87,'Assumption Table'!$B$83:$D$101,3,FALSE)*B$51 -> 1820.8563 | C87: =VLOOKUP($A87,'Assumption Table'!$B$83:$D$101,3,FALSE)*C$51 -> 3518.6455 | D87: =VLOOKUP($A87,'Assumption Table'!$B$83:$D$101,3,FALSE)*D$51 -> 6871.3249 | E87: =VLOOKUP($A87,'Assumption Table'!$B$83:$D$101,3,FALSE)*E$51 -> 4824.3962 | F87: =VLOOKUP($A87,'Assumption Table'!$B$83:$D$101,3,FALSE)*F$51 -> 6475.1693 | G87: =VLOOKUP($A87,'Assumption Table'!$B$83:$D$101,3,FALSE)*G$51 -> 11097.911 | H87: =VLOOKUP($A87,'Assumption Table'!$B$83:$D$101,3,FALSE)*H$51 -> 10688.881 | I87: =VLOOKUP($A87,'Assumption Table'!$B$83:$D$101,3,FALSE)*I$51 -> 14941.515 | ... BI87: =VLOOKUP($A87,'Assumption Table'!$B$83:$D$101,3,FALSE)*BI$51 -> 191720.62 | BJ87: =A87 -> Computers and Workstations | BK87: =SUMIFS($B87:$BI87,$B$4:$BI$4,"<=12") -> 133733.68 | BL87: =SUMIFS($B87:$BI87,$B$4:$BI$4,"<=24",$B$4:$BI$4,">12") -> 431803.01 | BM87: =SUMIFS($B87:$BI87,$B$4:$BI$4,"<=36",$B$4:$BI$4,">24") -> 758092.3 | BN87: =SUMIFS($B87:$BI87,$B$4:$BI$4,"<=48",$B$4:$BI$4,">36") -> 1093962.6 | BO87: =SUMIFS($B87:$BI87,$B$4:$BI$4,"<=60",$B$4:$BI$4,">48") -> 1764369.4
A88: Storage Devices | B88: =VLOOKUP($A88,'Assumption Table'!$B$83:$D$101,3,FALSE)*B$51 -> 3641.7126 | C88: =VLOOKUP($A88,'Assumption Table'!$B$83:$D$101,3,FALSE)*C$51 -> 7037.2911 | D88: =VLOOKUP($A88,'Assumption Table'!$B$83:$D$101,3,FALSE)*D$51 -> 13742.65 | E88: =VLOOKUP($A88,'Assumption Table'!$B$83:$D$101,3,FALSE)*E$51 -> 9648.7924 | F88: =VLOOKUP($A88,'Assumption Table'!$B$83:$D$101,3,FALSE)*F$51 -> 12950.339 | G88: =VLOOKUP($A88,'Assumption Table'!$B$83:$D$101,3,FALSE)*G$51 -> 22195.822 | H88: =VLOOKUP($A88,'Assumption Table'!$B$83:$D$101,3,FALSE)*H$51 -> 21377.763 | I88: =VLOOKUP($A88,'Assumption Table'!$B$83:$D$101,3,FALSE)*I$51 -> 29883.031 | ... BI88: =VLOOKUP($A88,'Assumption Table'!$B$83:$D$101,3,FALSE)*BI$51 -> 383441.25 | BJ88: =A88 -> Storage Devices | BK88: =SUMIFS($B88:$BI88,$B$4:$BI$4,"<=12") -> 267467.37 | BL88: =SUMIFS($B88:$BI88,$B$4:$BI$4,"<=24",$B$4:$BI$4,">12") -> 863606.02 | BM88: =SUMIFS($B88:$BI88,$B$4:$BI$4,"<=36",$B$4:$BI$4,">24") -> 1516184.6 | BN88: =SUMIFS($B88:$BI88,$B$4:$BI$4,"<=48",$B$4:$BI$4,">36") -> 2187925.1 | BO88: =SUMIFS($B88:$BI88,$B$4:$BI$4,"<=60",$B$4:$BI$4,">48") -> 3528738.8
A89: Development Costs | BJ89: =A89 -> Development Costs
A90: Product Development | B90: =VLOOKUP($A90,'Assumption Table'!$B$83:$D$101,3,FALSE)*B$51 -> 9104.2816 | C90: =VLOOKUP($A90,'Assumption Table'!$B$83:$D$101,3,FALSE)*C$51 -> 17593.228 | D90: =VLOOKUP($A90,'Assumption Table'!$B$83:$D$101,3,FALSE)*D$51 -> 34356.625 | E90: =VLOOKUP($A90,'Assumption Table'!$B$83:$D$101,3,FALSE)*E$51 -> 24121.981 | F90: =VLOOKUP($A90,'Assumption Table'!$B$83:$D$101,3,FALSE)*F$51 -> 32375.847 | G90: =VLOOKUP($A90,'Assumption Table'!$B$83:$D$101,3,FALSE)*G$51 -> 55489.555 | H90: =VLOOKUP($A90,'Assumption Table'!$B$83:$D$101,3,FALSE)*H$51 -> 53444.407 | I90: =VLOOKUP($A90,'Assumption Table'!$B$83:$D$101,3,FALSE)*I$51 -> 74707.576 | ... BI90: =VLOOKUP($A90,'Assumption Table'!$B$83:$D$101,3,FALSE)*BI$51 -> 958603.11 | BJ90: =A90 -> Product Development | BK90: =SUMIFS($B90:$BI90,$B$4:$BI$4,"<=12") -> 668668.42 | BL90: =SUMIFS($B90:$BI90,$B$4:$BI$4,"<=24",$B$4:$BI$4,">12") -> 2159015.1 | BM90: =SUMIFS($B90:$BI90,$B$4:$BI$4,"<=36",$B$4:$BI$4,">24") -> 3790461.5 | BN90: =SUMIFS($B90:$BI90,$B$4:$BI$4,"<=48",$B$4:$BI$4,">36") -> 5469812.8 | BO90: =SUMIFS($B90:$BI90,$B$4:$BI$4,"<=60",$B$4:$BI$4,">48") -> 8821847
A91: Research and Development | B91: =VLOOKUP($A91,'Assumption Table'!$B$83:$D$101,3,FALSE)*B$51 -> 3641.7126 | C91: =VLOOKUP($A91,'Assumption Table'!$B$83:$D$101,3,FALSE)*C$51 -> 7037.2911 | D91: =VLOOKUP($A91,'Assumption Table'!$B$83:$D$101,3,FALSE)*D$51 -> 13742.65 | E91: =VLOOKUP($A91,'Assumption Table'!$B$83:$D$101,3,FALSE)*E$51 -> 9648.7924 | F91: =VLOOKUP($A91,'Assumption Table'!$B$83:$D$101,3,FALSE)*F$51 -> 12950.339 | G91: =VLOOKUP($A91,'Assumption Table'!$B$83:$D$101,3,FALSE)*G$51 -> 22195.822 | H91: =VLOOKUP($A91,'Assumption Table'!$B$83:$D$101,3,FALSE)*H$51 -> 21377.763 | I91: =VLOOKUP($A91,'Assumption Table'!$B$83:$D$101,3,FALSE)*I$51 -> 29883.031 | ... BI91: =VLOOKUP($A91,'Assumption Table'!$B$83:$D$101,3,FALSE)*BI$51 -> 383441.25 | BJ91: =A91 -> Research and Development | BK91: =SUMIFS($B91:$BI91,$B$4:$BI$4,"<=12") -> 267467.37 | BL91: =SUMIFS($B91:$BI91,$B$4:$BI$4,"<=24",$B$4:$BI$4,">12") -> 863606.02 | BM91: =SUMIFS($B91:$BI91,$B$4:$BI$4,"<=36",$B$4:$BI$4,">24") -> 1516184.6 | BN91: =SUMIFS($B91:$BI91,$B$4:$BI$4,"<=48",$B$4:$BI$4,">36") -> 2187925.1 | BO91: =SUMIFS($B91:$BI91,$B$4:$BI$4,"<=60",$B$4:$BI$4,">48") -> 3528738.8
A92: Intellectual Property | BJ92: =A92 -> Intellectual Property
A93: Patents and Trademarks | B93: =VLOOKUP($A93,'Assumption Table'!$B$83:$D$101,3,FALSE)*B$51 -> 910.42816 | C93: =VLOOKUP($A93,'Assumption Table'!$B$83:$D$101,3,FALSE)*C$51 -> 1759.3228 | D93: =VLOOKUP($A93,'Assumption Table'!$B$83:$D$101,3,FALSE)*D$51 -> 3435.6625 | E93: =VLOOKUP($A93,'Assumption Table'!$B$83:$D$101,3,FALSE)*E$51 -> 2412.1981 | F93: =VLOOKUP($A93,'Assumption Table'!$B$83:$D$101,3,FALSE)*F$51 -> 3237.5847 | G93: =VLOOKUP($A93,'Assumption Table'!$B$83:$D$101,3,FALSE)*G$51 -> 5548.9555 | H93: =VLOOKUP($A93,'Assumption Table'!$B$83:$D$101,3,FALSE)*H$51 -> 5344.4407 | I93: =VLOOKUP($A93,'Assumption Table'!$B$83:$D$101,3,FALSE)*I$51 -> 7470.7576 | ... BI93: =VLOOKUP($A93,'Assumption Table'!$B$83:$D$101,3,FALSE)*BI$51 -> 95860.311 | BJ93: =A93 -> Patents and Trademarks | BK93: =SUMIFS($B93:$BI93,$B$4:$BI$4,"<=12") -> 66866.842 | BL93: =SUMIFS($B93:$BI93,$B$4:$BI$4,"<=24",$B$4:$BI$4,">12") -> 215901.51 | BM93: =SUMIFS($B93:$BI93,$B$4:$BI$4,"<=36",$B$4:$BI$4,">24") -> 379046.15 | BN93: =SUMIFS($B93:$BI93,$B$4:$BI$4,"<=48",$B$4:$BI$4,">36") -> 546981.28 | BO93: =SUMIFS($B93:$BI93,$B$4:$BI$4,"<=60",$B$4:$BI$4,">48") -> 882184.7
A94: Proprietary Technology | B94: =VLOOKUP($A94,'Assumption Table'!$B$83:$D$101,3,FALSE)*B$51 -> 3641.7126 | C94: =VLOOKUP($A94,'Assumption Table'!$B$83:$D$101,3,FALSE)*C$51 -> 7037.2911 | D94: =VLOOKUP($A94,'Assumption Table'!$B$83:$D$101,3,FALSE)*D$51 -> 13742.65 | E94: =VLOOKUP($A94,'Assumption Table'!$B$83:$D$101,3,FALSE)*E$51 -> 9648.7924 | F94: =VLOOKUP($A94,'Assumption Table'!$B$83:$D$101,3,FALSE)*F$51 -> 12950.339 | G94: =VLOOKUP($A94,'Assumption Table'!$B$83:$D$101,3,FALSE)*G$51 -> 22195.822 | H94: =VLOOKUP($A94,'Assumption Table'!$B$83:$D$101,3,FALSE)*H$51 -> 21377.763 | I94: =VLOOKUP($A94,'Assumption Table'!$B$83:$D$101,3,FALSE)*I$51 -> 29883.031 | ... BI94: =VLOOKUP($A94,'Assumption Table'!$B$83:$D$101,3,FALSE)*BI$51 -> 383441.25 | BJ94: =A94 -> Proprietary Technology | BK94: =SUMIFS($B94:$BI94,$B$4:$BI$4,"<=12") -> 267467.37 | BL94: =SUMIFS($B94:$BI94,$B$4:$BI$4,"<=24",$B$4:$BI$4,">12") -> 863606.02 | BM94: =SUMIFS($B94:$BI94,$B$4:$BI$4,"<=36",$B$4:$BI$4,">24") -> 1516184.6 | BN94: =SUMIFS($B94:$BI94,$B$4:$BI$4,"<=48",$B$4:$BI$4,">36") -> 2187925.1 | BO94: =SUMIFS($B94:$BI94,$B$4:$BI$4,"<=60",$B$4:$BI$4,">48") -> 3528738.8
A95: Cloud Services | BJ95: =A95 -> Cloud Services
A96: Long-term Cloud Contracts | B96: =VLOOKUP($A96,'Assumption Table'!$B$83:$D$101,3,FALSE)*B$51 -> 5462.5689 | C96: =VLOOKUP($A96,'Assumption Table'!$B$83:$D$101,3,FALSE)*C$51 -> 10555.937 | D96: =VLOOKUP($A96,'Assumption Table'!$B$83:$D$101,3,FALSE)*D$51 -> 20613.975 | E96: =VLOOKUP($A96,'Assumption Table'!$B$83:$D$101,3,FALSE)*E$51 -> 14473.189 | F96: =VLOOKUP($A96,'Assumption Table'!$B$83:$D$101,3,FALSE)*F$51 -> 19425.508 | G96: =VLOOKUP($A96,'Assumption Table'!$B$83:$D$101,3,FALSE)*G$51 -> 33293.733 | H96: =VLOOKUP($A96,'Assumption Table'!$B$83:$D$101,3,FALSE)*H$51 -> 32066.644 | I96: =VLOOKUP($A96,'Assumption Table'!$B$83:$D$101,3,FALSE)*I$51 -> 44824.546 | ... BI96: =VLOOKUP($A96,'Assumption Table'!$B$83:$D$101,3,FALSE)*BI$51 -> 575161.87 | BJ96: =A96 -> Long-term Cloud Contracts | BK96: =SUMIFS($B96:$BI96,$B$4:$BI$4,"<=12") -> 401201.05 | BL96: =SUMIFS($B96:$BI96,$B$4:$BI$4,"<=24",$B$4:$BI$4,">12") -> 1295409 | BM96: =SUMIFS($B96:$BI96,$B$4:$BI$4,"<=36",$B$4:$BI$4,">24") -> 2274276.9 | BN96: =SUMIFS($B96:$BI96,$B$4:$BI$4,"<=48",$B$4:$BI$4,">36") -> 3281887.7 | BO96: =SUMIFS($B96:$BI96,$B$4:$BI$4,"<=60",$B$4:$BI$4,">48") -> 5293108.2
A97: Security | BJ97: =A97 -> Security
A98: Cybersecurity Infrastructure | B98: =VLOOKUP($A98,'Assumption Table'!$B$83:$D$101,3,FALSE)*B$51 -> 3641.7126 | C98: =VLOOKUP($A98,'Assumption Table'!$B$83:$D$101,3,FALSE)*C$51 -> 7037.2911 | D98: =VLOOKUP($A98,'Assumption Table'!$B$83:$D$101,3,FALSE)*D$51 -> 13742.65 | E98: =VLOOKUP($A98,'Assumption Table'!$B$83:$D$101,3,FALSE)*E$51 -> 9648.7924 | F98: =VLOOKUP($A98,'Assumption Table'!$B$83:$D$101,3,FALSE)*F$51 -> 12950.339 | G98: =VLOOKUP($A98,'Assumption Table'!$B$83:$D$101,3,FALSE)*G$51 -> 22195.822 | H98: =VLOOKUP($A98,'Assumption Table'!$B$83:$D$101,3,FALSE)*H$51 -> 21377.763 | I98: =VLOOKUP($A98,'Assumption Table'!$B$83:$D$101,3,FALSE)*I$51 -> 29883.031 | ... BI98: =VLOOKUP($A98,'Assumption Table'!$B$83:$D$101,3,FALSE)*BI$51 -> 383441.25 | BJ98: =A98 -> Cybersecurity Infrastructure | BK98: =SUMIFS($B98:$BI98,$B$4:$BI$4,"<=12") -> 267467.37 | BL98: =SUMIFS($B98:$BI98,$B$4:$BI$4,"<=24",$B$4:$BI$4,">12") -> 863606.02 | BM98: =SUMIFS($B98:$BI98,$B$4:$BI$4,"<=36",$B$4:$BI$4,">24") -> 1516184.6 | BN98: =SUMIFS($B98:$BI98,$B$4:$BI$4,"<=48",$B$4:$BI$4,">36") -> 2187925.1 | BO98: =SUMIFS($B98:$BI98,$B$4:$BI$4,"<=60",$B$4:$BI$4,">48") -> 3528738.8
BJ99: =A99 -> 0
A100: Increment | BJ100: =A100 -> Increment
B101: 1 | C101: 2 | D101: 3 | E101: 4 | F101: 5 | G101: 6 | H101: 7 | I101: 8 | J101: 9 | K101: 10 | L101: 11 | M101: 12 | N101: 13 | O101: 14 | P101: 15 | Q101: 16 | R101: 17 | S101: 18 | T101: 19 | U101: 20 | V101: 21 | W101: 22 | X101: 23 | Y101: 24 | Z101: 25 | AA101: 26 | AB101: 27 | AC101: 28 | AD101: 29 | AE101: 30 | AF101: 31 | AG101: 32 | AH101: 33 | AI101: 34 | AJ101: 35 | AK101: 36 | AL101: 37 | AM101: 38 | AN101: 39 | AO101: 40 | AP101: 41 | AQ101: 42 | AR101: 43 | AS101: 44 | AT101: 45 | AU101: 46 | AV101: 47 | AW101: 48 | AX101: 49 | AY101: 50 | AZ101: 51 | BA101: 52 | BB101: 53 | BC101: 54 | BD101: 55 | BE101: 56 | BF101: 57 | BG101: 58 | BH101: 59 | BI101: 60 | BJ101: =A101 -> 0 | BK101: 1 | BL101: 2 | BM101: 3 | BN101: 4 | BO101: 5
...

Sheet Valuation Model
A1: Valuation Model
B3: Cost of Equity | C3: ='Assumption Table'!C129 -> 0.119
B4: WACC | C4: ='Assumption Table'!C139 -> 0.092666667
B5: Sustainable Long Term Growth Rate | C5: ='Assumption Table'!C142 -> 0.04 | Q5: ^If you can instead of adding cell E18 to M10 add the average from Monte Carlo Sim to M10 as the final estimated value
F6: 1 | G6: 2 | H6: 3 | I6: 4 | J6: 5
D7: In $
D9: FCF to Equity
D10: Net Income | F10: ='Projection Model'!BK220 -> 1610832.6 | G10: ='Projection Model'!BL220 -> 5492577.7 | H10: ='Projection Model'!BM220 -> 9719334.1 | I10: ='Projection Model'!BN220 -> 12252597 | J10: ='Projection Model'!BO220 -> 22109459
D11: Depreciation | F11: ='Projection Model'!BK168 -> 48624.081 | G11: ='Projection Model'!BL168 -> 156862.58 | H11: ='Projection Model'!BM168 -> 275359.19 | I11: ='Projection Model'!BN168 -> 397452.46 | J11: ='Projection Model'!BO168 -> 640851.26
D12: CAPEX | F12: =-'Projection Model'!BK122 -> -600258 | G12: =-'Projection Model'!BL122 -> -1258242.2 | H12: =-'Projection Model'!BM122 -> -4557941.5 | I12: =-'Projection Model'!BN122 -> -4137755.3 | J12: =-'Projection Model'!BO122 -> -6089031.9
D13: Changes in working capital | F13: =-'Projection Model'!BK192 -> -456810.04 | G13: =-'Projection Model'!BL192 -> -2306534.6 | H13: =-'Projection Model'!BM192 -> -2516512 | I13: =-'Projection Model'!BN192 -> -2334773.9 | J13: =-'Projection Model'!BO192 -> -5293809.7
D15: FCF to Equity (NI+Dep-Capex-chge NWC | F15: =SUM(F10:F13) -> 602388.66 | G15: =SUM(G10:G13) -> 2084663.4 | H15: =SUM(H10:H13) -> 2920239.8 | I15: =SUM(I10:I13) -> 6177519.9 | J15: =SUM(J10:J13) -> 11367469
D16: Terminal Value at end of year 5(Second Stage, Terminal Value) | J16: =J15*(1+C5)/(C3-C5) -> 1.4964769e+08
D17: Total FCF to Equity ( both first stage and second stage) | F17: =F15 -> 602388.66 | G17: =G15 -> 2084663.4 | H17: =H15 -> 2920239.8 | I17: =I15 -> 6177519.9 | J17: =J15 -> 11367469
D18: Total Equity Value | E18: {=NPV(C3,F17:J17)} -> 14706385
D19: Total number of Shares Outstanding | E19: ='Assumption Table'!C144 -> 1000000
D20: Per Share | E20: =E18/E19 -> 14.706385
D22: Total FCF to the Firm
D23: After Tax Interest Expense | F23: ='Projection Model'!BK214*(1-'Assumption Table'!$C$110) -> 153376.88 | G23: ='Projection Model'!BL214*(1-'Assumption Table'!$C$110) -> 143699.09 | H23: ='Projection Model'!BM214*(1-'Assumption Table'!$C$110) -> 134631.95 | I23: ='Projection Model'!BN214*(1-'Assumption Table'!$C$110) -> 126136.94 | J23: ='Projection Model'!BO214*(1-'Assumption Table'!$C$110) -> 118177.94
D25: Total FCF to the Firm (Total FCF Equity + After tax Interest Expense) | F25: =F15+F23 -> 755765.54 | G25: =G15+G23 -> 2228362.5 | H25: =H15+H23 -> 3054871.8 | I25: =I15+I23 -> 6303656.9 | J25: =J15+J23 -> 11485647
D26: Terminal Value at end of year 5 | J26: =J25*(1+C5)/(C4-C5) -> 2.2680518e+08
D27: Total FCF to the Firm | F27: =F25 -> 755765.54 | G27: =G25 -> 2228362.5 | H27: =H25 -> 3054871.8 | I27: =I25 -> 6303656.9 | J27: =J25+J26 -> 2.3829083e+08
D28: Enterprise Value | E28: {=NPV(C4,F27:J27)} -> 1.6231407e+08
D29: Less Total Debt | E29: ='Projection Model'!B177 -> 4972916.7
D30: Total Equity Value | E30: =E28-E29 -> 1.5734115e+08
D31: Number of Shares | E31: =E19 -> 1000000
D32: Equity Value Per Share | E32: =E30/E31 -> 157.34115
D38: Inputs | E38: Change/10% | F38: Input Change | G38: Estimated Change for Input | H38: Total Decimal Change | I38: Final Estimated Value
D39: active users per support agent | E39: 0.15319435 | F39: 0 | G39: =((F39)/0.1)*E39 -> 0 | H39: =SUM(G39:G62) -> 0 | I39: =E18*(1+H39) -> 14706385
D40: Retention rate | E40: 0.1 | F40: 0 | G40: =((F40)/0.1)*E40 -> 0
D41: item 3 pricing | E41: 0.094328771 | F41: 0 | G41: =((F41)/0.1)*E41 -> 0
D42: item 3 ART | E42: 0.0943 | F42: 0 | G42: =((F42)/0.1)*E42 -> 0
D43: Organic Downloads Mean | E43: 0.068 | F43: 0 | G43: =((F43)/0.1)*E43 -> 0
D44: Monthly conversion rate | E44: 0.0389 | F44: 0 | G44: =((F44)/0.1)*E44 -> 0
D45: Monthly Plan | E45: 0.0389 | F45: 0 | G45: =((F45)/0.1)*E45 -> 0
D46: item 1 ART | E46: 0.036 | F46: 0 | G46: =((F46)/0.1)*E46 -> 0
D47: item 4 ART | E47: 0.0354 | F47: 0 | G47: =((F47)/0.1)*E47 -> 0
D48: item 4 pricing | E48: 0.035378744 | F48: 0 | G48: =((F48)/0.1)*E48 -> 0
D49: item 1 pricing | E49: 0.035320671 | F49: 0 | G49: =((F49)/0.1)*E49 -> 0
D50: item 2 pricing | E50: 0.035038099 | F50: 0 | G50: =((F50)/0.1)*E50 -> 0
D51: item 2 ART | E51: 0.035 | F51: 0 | G51: =((F51)/0.1)*E51 -> 0
... D62: Platform fees | E62: -0.29018113 | F62: 0 | G62: =((F62)/0.1)*E62 -> 0
